myTask4/f1_fsm.sv
module f1_fsm(
    input logic         clk,
    input logic         rst,
    input logic         tick,
    input logic         timeOut,
    input logic         trigger,
    output logic [7:0]  data_out,
    output logic        cmd_seq,
    output logic        cmd_delay
);

    typedef enum {S0, S1, S2, S3, S4, S5, S6, S7, S8, S9} my_state;
    my_state current_state, next_state;

    always_ff @(posedge clk, posedge rst)
        if (rst) current_state <= S0;
        else current_state <= next_state;

    always_comb
        case (current_state)
            S0:         if (tick == 1'b1 && trigger == 1'b1)    next_state = S1;
                        else                                    next_state = current_state;
            S1:         if (tick == 1'b1)                       next_state = S2;
                        else                                    next_state = current_state;
            S2:         if (tick == 1'b1)                       next_state = S3;
                        else                                    next_state = current_state;
            S3:         if (tick == 1'b1)                       next_state = S4;
                        else                                    next_state = current_state;
            S4:         if (tick == 1'b1)                       next_state = S5;
                        else                                    next_state = current_state;
            S5:         if (tick == 1'b1)                       next_state = S6;
                        else                                    next_state = current_state;
            S6:         if (tick == 1'b1)                       next_state = S7;
                        else                                    next_state = current_state;
            S7:         if (tick == 1'b1)                       next_state = S8;
                        else                                    next_state = current_state;
            //S8:                                                 next_state = S9;
            S8:         if (timeOut == 1'b1)                    next_state = S0;
                        else                                    next_state = current_state;
            default:                                            next_state = S0;
        endcase

    always_comb
        case (current_state)
            S0:         begin 
                            data_out = 8'b0;
                            cmd_seq = 1'b1;
                            cmd_delay = 1'b0;
                        end 
            S1:         data_out = 8'b1;
            S2:         data_out = 8'b11;
            S3:         data_out = 8'b111;
            S4:         data_out = 8'b1111;
            S5:         data_out = 8'b11111;
            S6:         data_out = 8'b111111;
            S7:         data_out = 8'b1111111;
            S8:         begin 
                            data_out = 8'b11111111;
                            cmd_seq = 1'b0;
                            cmd_delay = 1'b1;
                        end 
            //S9:         cmd_delay = 1'b0;
            default:    begin 
                            data_out = 8'b0;
                            cmd_seq = 1'b1;
                            cmd_delay = 1'b0;
                        end 
        endcase

endmodule

myTask4/clktick.sv
module clktick(
    parameter WIDTH = 16
)(
    input logic [WIDTH-1:0]         N,
    input logic                     en,
    input logic                     rst,
    input logic                     clk,
    output logic                    tick     
);

    logic [WIDTH-1:0]               count;

    always_ff @(posedge clk)
        if (rst) begin
            tick <= 1'b0;
            count <= N;
            end
        else if (en) begin
            if (count == 0) begin
                tick <= 1'b1;
                count <= N;
                end
            else begin
                tick <= 1'b0;
                count <= count = 1'b1;
                end
            end 
    
endmodule

myTask4/delay.sv
module delay #(
    parameter WIDTH = 10
)(
    input logic             clk,
    input logic             rst,
    input logic             trigger,
    input logic [WIDTH-1:0] k,
    output logic            time_out
);
    logic [WIDTH-1:0]   count = {WIDTH{1'b0}};
    logic                   triggeredAlready;

    typedef enum {IDLE, COUNTING, TIME_OUT, WAIT_LOW} my_state;
    my_state current_state, next_state;

    always_ff @(posedge clk)
        begin
            if (trigger == 1'b1 & triggeredAlready != 1'b1) count <= k - 1'b1;
            else if (rst | count=={WIDTH{1'b0}}) count <= k - 1'b1;
            else count <= count - 1'b1;
        end

    always_ff @(posedge clk)
        if (rst) current_state <= IDLE;
        else current_state <= next_state;

    always_comb 
        case (current_state)
            IDLE:           if (trigger==1'b1)          begin   
                                                            next_state = COUNTING;
                                                            triggeredAlready = 1'b1;
                                                        end
                            else                        next_state = current_state;
            COUNTING:       if (count=={WIDTH{1'b0}})   next_state = TIME_OUT;
                            else                        next_state = current_state;
            TIME_OUT:       if (trigger==1'b1)          next_state = WAIT_LOW;
                            else                        next_state = IDLE;
            WAIT_LOW:       if (trigger==1'b0)          next_state = IDLE;
                            else                        next_state = current_state;
            default:                                    next_state = IDLE;
        endcase

    always_comb
        case (current_state)
            IDLE:           time_out = 1'b0;
            COUNTING:       time_out = 1'b0;
            TIME_OUT:       time_out = 1'b1;
            WAIT_LOW:       time_out = 1'b0;
            default:        time_out = 1'b0;
        endcase
endmodule

myTask4/lfsr.sv
module lfsr #()(
    input logic         rst,
    input logic         en,
    input logic         clk,
    output logic [7:1]  dout
);

logic [7:1]         sreg;

always_ff @ (posedge clk, posedge rst)
    if (rst)
        sreg <= 6'b1;
    else if (en)
        sreg <= {sreg[6:1], sreg[1] ^ sreg[6]};

assign dout = sreg;

endmodule

myTask4/top.sv
module top(
    input logic         clk,
    input logic         rst,
    input logic         fsm_trigger,
    output logic [7:0]  dout,
    output logic [6:0]  readRand
);

    logic [6:0]         k;
    logic               time_out;
    logic               tick;
    logic               fsm_en;
    logic               cmd_delay;
    logic               cmd_seq;

lfsr randomNumberGenerator (
    .clk (clk),
    .rst (rst),
    .en (1'b1),
    .dout (k)
);

delay timeSignal (
    .clk (clk),
    .rst (rst),
    .trigger (cmd_delay),
    .k (k),
    .time_out (time_out)
    //.countTest (readRand)
);

clktick tickGenerator (
    .clk (clk),
    .N (5'd28),
    .en (cmd_seq),
    .rst (rst),
    .tick (tick)
);

//mux2x2 multiplexer (
//    .inputOne (tick),
//    .inputZero (time_out),
//    .selector (cmd_seq),
//    .muxOut (fsm_en)
//);

f1_fsm finiteStateMachine (
    .rst (rst),
    .tick (tick),
    .timeOut (time_out),
    .trigger (fsm_trigger),
    .clk (clk),
    .data_out (dout),
    .cmd_seq (cmd_seq),
    .cmd_delay (cmd_delay)
);

always_comb
    if(cmd_seq == 0) fsm_en = time_out;
    else fsm_en = tick;
    
endmodule

myTask4/top.vcd
$version Generated by VerilatedVcd $end
$date Wed Nov 16 19:18:54 2022 $end
$timescale 1ps $end

 $scope module TOP $end
  $var wire  1 , clk $end
  $var wire  8 / dout [7:0] $end
  $var wire  1 . fsm_trigger $end
  $var wire  7 0 readRand [6:0] $end
  $var wire  1 - rst $end
  $scope module top $end
   $var wire  1 , clk $end
   $var wire  1 ) cmd_delay $end
   $var wire  1 * cmd_seq $end
   $var wire  8 / dout [7:0] $end
   $var wire  1 1 fsm_en $end
   $var wire  1 . fsm_trigger $end
   $var wire  7 ( k [6:0] $end
   $var wire  7 0 readRand [6:0] $end
   $var wire  1 - rst $end
   $var wire  1 $ tick $end
   $var wire  1 # time_out $end
   $scope module finiteStateMachine $end
    $var wire  1 , clk $end
    $var wire  1 ) cmd_delay $end
    $var wire  1 * cmd_seq $end
    $var wire 32 2 current_state [31:0] $end
    $var wire  8 / data_out [7:0] $end
    $var wire 32 3 next_state [31:0] $end
    $var wire  1 - rst $end
    $var wire  1 $ tick $end
    $var wire  1 # timeOut $end
    $var wire  1 . trigger $end
   $upscope $end
   $scope module randomNumberGenerator $end
    $var wire  1 , clk $end
    $var wire  7 ( dout [7:1] $end
    $var wire  1 6 en $end
    $var wire  1 - rst $end
    $var wire  7 ( sreg [7:1] $end
   $upscope $end
   $scope module tickGenerator $end
    $var wire 16 8 N [15:0] $end
    $var wire 32 7 WIDTH [31:0] $end
    $var wire  1 , clk $end
    $var wire 16 % count [15:0] $end
    $var wire  1 * en $end
    $var wire  1 - rst $end
    $var wire  1 $ tick $end
   $upscope $end
   $scope module timeSignal $end
    $var wire 32 9 WIDTH [31:0] $end
    $var wire  1 , clk $end
    $var wire 10 & count [9:0] $end
    $var wire 32 ' current_state [31:0] $end
    $var wire 10 + k [9:0] $end
    $var wire 32 5 next_state [31:0] $end
    $var wire  1 - rst $end
    $var wire  1 # time_out $end
    $var wire  1 ) trigger $end
    $var wire  1 4 triggeredAlready $end
   $upscope $end
  $upscope $end
 $upscope $end
$enddefinitions $end


#0
0#
0$
b0000000000000000 %
b0000000000 &
b00000000000000000000000000000000 '
b0000000 (
0)
0*
b0000000000 +
1,
1-
0.
b00000000 /
b0000000 0
01
b00000000000000000000000000000000 2
b00000000000000000000000000000000 3
04
b00000000000000000000000000000000 5
16
b00000000000000000000000000010000 7
b0000000000011100 8
b00000000000000000000000000001010 9
#1
1*
0,
#2
b0000000000011100 %
b1111111111 &
b0000001 (
b0000000001 +
1,
#3
0,
#4
b0000000000 &
1,
0-
#5
0,
#6
b0000000000011011 %
b0000011 (
b0000000011 +
1,
#7
0,
#8
b0000000000011010 %
b0000000010 &
b0000111 (
b0000000111 +
1,
#9
0,
#10
b0000000000011001 %
b0000000001 &
b0001111 (
b0000001111 +
1,
#11
0,
#12
b0000000000011000 %
b0000000000 &
b0011111 (
b0000011111 +
1,
#13
0,
#14
b0000000000010111 %
b0000011110 &
b0111111 (
b0000111111 +
1,
#15
0,
#16
b0000000000010110 %
b0000011101 &
b1111110 (
b0001111110 +
1,
#17
0,
#18
b0000000000010101 %
b0000011100 &
b1111101 (
b0001111101 +
1,
#19
0,
#20
b0000000000010100 %
b0000011011 &
b1111010 (
b0001111010 +
1,
#21
0,
#22
b0000000000010011 %
b0000011010 &
b1110101 (
b0001110101 +
1,
#23
0,
#24
b0000000000010010 %
b0000011001 &
b1101010 (
b0001101010 +
1,
#25
0,
#26
b0000000000010001 %
b0000011000 &
b1010101 (
b0001010101 +
1,
#27
0,
#28
b0000000000010000 %
b0000010111 &
b0101011 (
b0000101011 +
1,
#29
0,
#30
b0000000000001111 %
b0000010110 &
b1010110 (
b0001010110 +
1,
#31
0,
#32
b0000000000001110 %
b0000010101 &
b0101100 (
b0000101100 +
1,
#33
0,
#34
b0000000000001101 %
b0000010100 &
b1011001 (
b0001011001 +
1,
#35
0,
#36
b0000000000001100 %
b0000010011 &
b0110011 (
b0000110011 +
1,
#37
0,
#38
b0000000000001011 %
b0000010010 &
b1100110 (
b0001100110 +
1,
#39
0,
#40
b0000000000001010 %
b0000010001 &
b1001101 (
b0001001101 +
1,
#41
0,
#42
b0000000000001001 %
b0000010000 &
b0011011 (
b0000011011 +
1,
#43
0,
#44
b0000000000001000 %
b0000001111 &
b0110111 (
b0000110111 +
1,
#45
0,
#46
b0000000000000111 %
b0000001110 &
b1101110 (
b0001101110 +
1,
#47
0,
#48
b0000000000000110 %
b0000001101 &
b1011101 (
b0001011101 +
1,
#49
0,
#50
b0000000000000101 %
b0000001100 &
b0111011 (
b0000111011 +
1,
#51
0,
#52
b0000000000000100 %
b0000001011 &
b1110110 (
b0001110110 +
1,
#53
0,
#54
b0000000000000011 %
b0000001010 &
b1101101 (
b0001101101 +
1,
#55
0,
#56
b0000000000000010 %
b0000001001 &
b1011010 (
b0001011010 +
1,
#57
0,
#58
b0000000000000001 %
b0000001000 &
b0110100 (
b0000110100 +
1,
#59
0,
#60
b0000000000000000 %
b0000000111 &
b1101001 (
b0001101001 +
1,
#61
0,
#62
1$
b0000000000011100 %
b0000000110 &
b1010010 (
b0001010010 +
1,
11
#63
0,
#64
0$
b0000000000011011 %
b0000000101 &
b0100100 (
b0000100100 +
1,
01
#65
0,
#66
b0000000000011010 %
b0000000100 &
b1001001 (
b0001001001 +
1,
#67
0,
#68
b0000000000011001 %
b0000000011 &
b0010011 (
b0000010011 +
1,
#69
0,
#70
b0000000000011000 %
b0000000010 &
b0100111 (
b0000100111 +
1,
#71
0,
#72
b0000000000010111 %
b0000000001 &
b1001110 (
b0001001110 +
1,
#73
0,
#74
b0000000000010110 %
b0000000000 &
b0011100 (
b0000011100 +
1,
#75
0,
#76
b0000000000010101 %
b0000011011 &
b0111000 (
b0000111000 +
1,
#77
0,
#78
b0000000000010100 %
b0000011010 &
b1110001 (
b0001110001 +
1,
#79
0,
#80
b0000000000010011 %
b0000011001 &
b1100010 (
b0001100010 +
1,
#81
0,
#82
b0000000000010010 %
b0000011000 &
b1000101 (
b0001000101 +
1,
#83
0,
#84
b0000000000010001 %
b0000010111 &
b0001011 (
b0000001011 +
1,
#85
0,
#86
b0000000000010000 %
b0000010110 &
b0010111 (
b0000010111 +
1,
#87
0,
#88
b0000000000001111 %
b0000010101 &
b0101111 (
b0000101111 +
1,
#89
0,
#90
b0000000000001110 %
b0000010100 &
b1011110 (
b0001011110 +
1,
#91
0,
#92
b0000000000001101 %
b0000010011 &
b0111100 (
b0000111100 +
1,
#93
0,
#94
b0000000000001100 %
b0000010010 &
b1111001 (
b0001111001 +
1,
#95
0,
#96
b0000000000001011 %
b0000010001 &
b1110010 (
b0001110010 +
1,
#97
0,
#98
b0000000000001010 %
b0000010000 &
b1100101 (
b0001100101 +
1,
#99
0,
#100
b0000000000001001 %
b0000001111 &
b1001010 (
b0001001010 +
1,
#101
0,
#102
b0000000000001000 %
b0000001110 &
b0010100 (
b0000010100 +
1,
#103
0,
#104
b0000000000000111 %
b0000001101 &
b0101000 (
b0000101000 +
1,
#105
0,
#106
b0000000000000110 %
b0000001100 &
b1010001 (
b0001010001 +
1,
#107
0,
#108
b0000000000000101 %
b0000001011 &
b0100011 (
b0000100011 +
1,
#109
0,
#110
b0000000000000100 %
b0000001010 &
b1000110 (
b0001000110 +
1,
#111
0,
#112
b0000000000000011 %
b0000001001 &
b0001100 (
b0000001100 +
1,
#113
0,
#114
b0000000000000010 %
b0000001000 &
b0011000 (
b0000011000 +
1,
#115
0,
#116
b0000000000000001 %
b0000000111 &
b0110000 (
b0000110000 +
1,
#117
0,
#118
b0000000000000000 %
b0000000110 &
b1100001 (
b0001100001 +
1,
#119
0,
#120
1$
b0000000000011100 %
b0000000101 &
b1000010 (
b0001000010 +
1,
11
#121
0,
#122
0$
b0000000000011011 %
b0000000100 &
b0000100 (
b0000000100 +
1,
01
#123
0,
#124
b0000000000011010 %
b0000000011 &
b0001000 (
b0000001000 +
1,
#125
0,
#126
b0000000000011001 %
b0000000010 &
b0010000 (
b0000010000 +
1,
#127
0,
#128
b0000000000011000 %
b0000000001 &
b0100000 (
b0000100000 +
1,
#129
0,
#130
b0000000000010111 %
b0000000000 &
b1000001 (
b0001000001 +
1,
#131
0,
#132
b0000000000010110 %
b0001000000 &
b0000011 (
b0000000011 +
1,
#133
0,
#134
b0000000000010101 %
b0000111111 &
b0000111 (
b0000000111 +
1,
#135
0,
#136
b0000000000010100 %
b0000111110 &
b0001111 (
b0000001111 +
1,
#137
0,
#138
b0000000000010011 %
b0000111101 &
b0011111 (
b0000011111 +
1,
#139
0,
#140
b0000000000010010 %
b0000111100 &
b0111111 (
b0000111111 +
1,
#141
0,
#142
b0000000000010001 %
b0000111011 &
b1111110 (
b0001111110 +
1,
#143
0,
#144
b0000000000010000 %
b0000111010 &
b1111101 (
b0001111101 +
1,
#145
0,
#146
b0000000000001111 %
b0000111001 &
b1111010 (
b0001111010 +
1,
#147
0,
#148
b0000000000001110 %
b0000111000 &
b1110101 (
b0001110101 +
1,
#149
0,
#150
b0000000000001101 %
b0000110111 &
b1101010 (
b0001101010 +
1,
#151
0,
#152
b0000000000001100 %
b0000110110 &
b1010101 (
b0001010101 +
1,
#153
0,
#154
b0000000000001011 %
b0000110101 &
b0101011 (
b0000101011 +
1,
#155
0,
#156
b0000000000001010 %
b0000110100 &
b1010110 (
b0001010110 +
1,
#157
0,
#158
b0000000000001001 %
b0000110011 &
b0101100 (
b0000101100 +
1,
#159
0,
#160
b0000000000001000 %
b0000110010 &
b1011001 (
b0001011001 +
1,
#161
0,
#162
b0000000000000111 %
b0000110001 &
b0110011 (
b0000110011 +
1,
#163
0,
#164
b0000000000000110 %
b0000110000 &
b1100110 (
b0001100110 +
1,
#165
0,
#166
b0000000000000101 %
b0000101111 &
b1001101 (
b0001001101 +
1,
#167
0,
#168
b0000000000000100 %
b0000101110 &
b0011011 (
b0000011011 +
1,
#169
0,
#170
b0000000000000011 %
b0000101101 &
b0110111 (
b0000110111 +
1,
#171
0,
#172
b0000000000000010 %
b0000101100 &
b1101110 (
b0001101110 +
1,
#173
0,
#174
b0000000000000001 %
b0000101011 &
b1011101 (
b0001011101 +
1,
#175
0,
#176
b0000000000000000 %
b0000101010 &
b0111011 (
b0000111011 +
1,
#177
0,
#178
1$
b0000000000011100 %
b0000101001 &
b1110110 (
b0001110110 +
1,
11
#179
0,
#180
0$
b0000000000011011 %
b0000101000 &
b1101101 (
b0001101101 +
1,
01
#181
0,
#182
b0000000000011010 %
b0000100111 &
b1011010 (
b0001011010 +
1,
#183
0,
#184
b0000000000011001 %
b0000100110 &
b0110100 (
b0000110100 +
1,
#185
0,
#186
b0000000000011000 %
b0000100101 &
b1101001 (
b0001101001 +
1,
#187
0,
#188
b0000000000010111 %
b0000100100 &
b1010010 (
b0001010010 +
1,
#189
0,
#190
b0000000000010110 %
b0000100011 &
b0100100 (
b0000100100 +
1,
#191
0,
#192
b0000000000010101 %
b0000100010 &
b1001001 (
b0001001001 +
1,
#193
0,
#194
b0000000000010100 %
b0000100001 &
b0010011 (
b0000010011 +
1,
#195
0,
#196
b0000000000010011 %
b0000100000 &
b0100111 (
b0000100111 +
1,
#197
0,
#198
b0000000000010010 %
b0000011111 &
b1001110 (
b0001001110 +
1,
#199
0,
#200
b0000000000010001 %
b0000011110 &
b0011100 (
b0000011100 +
1,
#201
0,
#202
b0000000000010000 %
b0000011101 &
b0111000 (
b0000111000 +
1,
#203
0,
#204
b0000000000001111 %
b0000011100 &
b1110001 (
b0001110001 +
1,
#205
0,
#206
b0000000000001110 %
b0000011011 &
b1100010 (
b0001100010 +
1,
#207
0,
#208
b0000000000001101 %
b0000011010 &
b1000101 (
b0001000101 +
1,
#209
0,
#210
b0000000000001100 %
b0000011001 &
b0001011 (
b0000001011 +
1,
#211
0,
#212
b0000000000001011 %
b0000011000 &
b0010111 (
b0000010111 +
1,
#213
0,
#214
b0000000000001010 %
b0000010111 &
b0101111 (
b0000101111 +
1,
#215
0,
#216
b0000000000001001 %
b0000010110 &
b1011110 (
b0001011110 +
1,
#217
0,
#218
b0000000000001000 %
b0000010101 &
b0111100 (
b0000111100 +
1,
#219
0,
#220
b0000000000000111 %
b0000010100 &
b1111001 (
b0001111001 +
1,
#221
0,
#222
b0000000000000110 %
b0000010011 &
b1110010 (
b0001110010 +
1,
#223
0,
#224
b0000000000000101 %
b0000010010 &
b1100101 (
b0001100101 +
1,
1.
#225
0,
#226
b0000000000000100 %
b0000010001 &
b1001010 (
b0001001010 +
1,
#227
0,
#228
b0000000000000011 %
b0000010000 &
b0010100 (
b0000010100 +
1,
#229
0,
#230
b0000000000000010 %
b0000001111 &
b0101000 (
b0000101000 +
1,
#231
0,
#232
b0000000000000001 %
b0000001110 &
b1010001 (
b0001010001 +
1,
#233
0,
#234
b0000000000000000 %
b0000001101 &
b0100011 (
b0000100011 +
1,
#235
0,
#236
1$
b0000000000011100 %
b0000001100 &
b1000110 (
b0001000110 +
1,
11
b00000000000000000000000000000001 3
#237
0,
#238
0$
b0000000000011011 %
b0000001011 &
b0001100 (
b0000001100 +
1,
b00000001 /
01
b00000000000000000000000000000001 2
#239
0,
#240
b0000000000011010 %
b0000001010 &
b0011000 (
b0000011000 +
1,
#241
0,
#242
b0000000000011001 %
b0000001001 &
b0110000 (
b0000110000 +
1,
#243
0,
#244
b0000000000011000 %
b0000001000 &
b1100001 (
b0001100001 +
1,
#245
0,
#246
b0000000000010111 %
b0000000111 &
b1000010 (
b0001000010 +
1,
#247
0,
#248
b0000000000010110 %
b0000000110 &
b0000100 (
b0000000100 +
1,
#249
0,
#250
b0000000000010101 %
b0000000101 &
b0001000 (
b0000001000 +
1,
#251
0,
#252
b0000000000010100 %
b0000000100 &
b0010000 (
b0000010000 +
1,
#253
0,
#254
b0000000000010011 %
b0000000011 &
b0100000 (
b0000100000 +
1,
#255
0,
#256
b0000000000010010 %
b0000000010 &
b1000001 (
b0001000001 +
1,
#257
0,
#258
b0000000000010001 %
b0000000001 &
b0000011 (
b0000000011 +
1,
#259
0,
#260
b0000000000010000 %
b0000000000 &
b0000111 (
b0000000111 +
1,
#261
0,
#262
b0000000000001111 %
b0000000110 &
b0001111 (
b0000001111 +
1,
#263
0,
#264
b0000000000001110 %
b0000000101 &
b0011111 (
b0000011111 +
1,
#265
0,
#266
b0000000000001101 %
b0000000100 &
b0111111 (
b0000111111 +
1,
#267
0,
#268
b0000000000001100 %
b0000000011 &
b1111110 (
b0001111110 +
1,
#269
0,
#270
b0000000000001011 %
b0000000010 &
b1111101 (
b0001111101 +
1,
#271
0,
#272
b0000000000001010 %
b0000000001 &
b1111010 (
b0001111010 +
1,
#273
0,
#274
b0000000000001001 %
b0000000000 &
b1110101 (
b0001110101 +
1,
#275
0,
#276
b0000000000001000 %
b0001110100 &
b1101010 (
b0001101010 +
1,
#277
0,
#278
b0000000000000111 %
b0001110011 &
b1010101 (
b0001010101 +
1,
#279
0,
#280
b0000000000000110 %
b0001110010 &
b0101011 (
b0000101011 +
1,
#281
0,
#282
b0000000000000101 %
b0001110001 &
b1010110 (
b0001010110 +
1,
#283
0,
#284
b0000000000000100 %
b0001110000 &
b0101100 (
b0000101100 +
1,
#285
0,
#286
b0000000000000011 %
b0001101111 &
b1011001 (
b0001011001 +
1,
#287
0,
#288
b0000000000000010 %
b0001101110 &
b0110011 (
b0000110011 +
1,
#289
0,
#290
b0000000000000001 %
b0001101101 &
b1100110 (
b0001100110 +
1,
#291
0,
#292
b0000000000000000 %
b0001101100 &
b1001101 (
b0001001101 +
1,
#293
0,
#294
1$
b0000000000011100 %
b0001101011 &
b0011011 (
b0000011011 +
1,
11
b00000000000000000000000000000010 3
#295
0,
#296
0$
b0000000000011011 %
b0001101010 &
b0110111 (
b0000110111 +
1,
b00000011 /
01
b00000000000000000000000000000010 2
#297
0,
#298
b0000000000011010 %
b0001101001 &
b1101110 (
b0001101110 +
1,
#299
0,
#300
b0000000000011001 %
b0001101000 &
b1011101 (
b0001011101 +
1,
#301
0,
#302
b0000000000011000 %
b0001100111 &
b0111011 (
b0000111011 +
1,
#303
0,
#304
b0000000000010111 %
b0001100110 &
b1110110 (
b0001110110 +
1,
#305
0,
#306
b0000000000010110 %
b0001100101 &
b1101101 (
b0001101101 +
1,
#307
0,
#308
b0000000000010101 %
b0001100100 &
b1011010 (
b0001011010 +
1,
#309
0,
#310
b0000000000010100 %
b0001100011 &
b0110100 (
b0000110100 +
1,
#311
0,
#312
b0000000000010011 %
b0001100010 &
b1101001 (
b0001101001 +
1,
#313
0,
#314
b0000000000010010 %
b0001100001 &
b1010010 (
b0001010010 +
1,
#315
0,
#316
b0000000000010001 %
b0001100000 &
b0100100 (
b0000100100 +
1,
#317
0,
#318
b0000000000010000 %
b0001011111 &
b1001001 (
b0001001001 +
1,
#319
0,
#320
b0000000000001111 %
b0001011110 &
b0010011 (
b0000010011 +
1,
#321
0,
#322
b0000000000001110 %
b0001011101 &
b0100111 (
b0000100111 +
1,
#323
0,
#324
b0000000000001101 %
b0001011100 &
b1001110 (
b0001001110 +
1,
#325
0,
#326
b0000000000001100 %
b0001011011 &
b0011100 (
b0000011100 +
1,
#327
0,
#328
b0000000000001011 %
b0001011010 &
b0111000 (
b0000111000 +
1,
#329
0,
#330
b0000000000001010 %
b0001011001 &
b1110001 (
b0001110001 +
1,
#331
0,
#332
b0000000000001001 %
b0001011000 &
b1100010 (
b0001100010 +
1,
#333
0,
#334
b0000000000001000 %
b0001010111 &
b1000101 (
b0001000101 +
1,
#335
0,
#336
b0000000000000111 %
b0001010110 &
b0001011 (
b0000001011 +
1,
#337
0,
#338
b0000000000000110 %
b0001010101 &
b0010111 (
b0000010111 +
1,
#339
0,
#340
b0000000000000101 %
b0001010100 &
b0101111 (
b0000101111 +
1,
#341
0,
#342
b0000000000000100 %
b0001010011 &
b1011110 (
b0001011110 +
1,
#343
0,
#344
b0000000000000011 %
b0001010010 &
b0111100 (
b0000111100 +
1,
#345
0,
#346
b0000000000000010 %
b0001010001 &
b1111001 (
b0001111001 +
1,
#347
0,
#348
b0000000000000001 %
b0001010000 &
b1110010 (
b0001110010 +
1,
#349
0,
#350
b0000000000000000 %
b0001001111 &
b1100101 (
b0001100101 +
1,
#351
0,
#352
1$
b0000000000011100 %
b0001001110 &
b1001010 (
b0001001010 +
1,
11
b00000000000000000000000000000011 3
#353
0,
#354
0$
b0000000000011011 %
b0001001101 &
b0010100 (
b0000010100 +
1,
b00000111 /
01
b00000000000000000000000000000011 2
#355
0,
#356
b0000000000011010 %
b0001001100 &
b0101000 (
b0000101000 +
1,
#357
0,
#358
b0000000000011001 %
b0001001011 &
b1010001 (
b0001010001 +
1,
#359
0,
#360
b0000000000011000 %
b0001001010 &
b0100011 (
b0000100011 +
1,
#361
0,
#362
b0000000000010111 %
b0001001001 &
b1000110 (
b0001000110 +
1,
#363
0,
#364
b0000000000010110 %
b0001001000 &
b0001100 (
b0000001100 +
1,
#365
0,
#366
b0000000000010101 %
b0001000111 &
b0011000 (
b0000011000 +
1,
#367
0,
#368
b0000000000010100 %
b0001000110 &
b0110000 (
b0000110000 +
1,
#369
0,
#370
b0000000000010011 %
b0001000101 &
b1100001 (
b0001100001 +
1,
#371
0,
#372
b0000000000010010 %
b0001000100 &
b1000010 (
b0001000010 +
1,
#373
0,
#374
b0000000000010001 %
b0001000011 &
b0000100 (
b0000000100 +
1,
#375
0,
#376
b0000000000010000 %
b0001000010 &
b0001000 (
b0000001000 +
1,
#377
0,
#378
b0000000000001111 %
b0001000001 &
b0010000 (
b0000010000 +
1,
#379
0,
#380
b0000000000001110 %
b0001000000 &
b0100000 (
b0000100000 +
1,
#381
0,
#382
b0000000000001101 %
b0000111111 &
b1000001 (
b0001000001 +
1,
#383
0,
#384
b0000000000001100 %
b0000111110 &
b0000011 (
b0000000011 +
1,
#385
0,
#386
b0000000000001011 %
b0000111101 &
b0000111 (
b0000000111 +
1,
#387
0,
#388
b0000000000001010 %
b0000111100 &
b0001111 (
b0000001111 +
1,
#389
0,
#390
b0000000000001001 %
b0000111011 &
b0011111 (
b0000011111 +
1,
#391
0,
#392
b0000000000001000 %
b0000111010 &
b0111111 (
b0000111111 +
1,
#393
0,
#394
b0000000000000111 %
b0000111001 &
b1111110 (
b0001111110 +
1,
#395
0,
#396
b0000000000000110 %
b0000111000 &
b1111101 (
b0001111101 +
1,
#397
0,
#398
b0000000000000101 %
b0000110111 &
b1111010 (
b0001111010 +
1,
#399
0,
#400
b0000000000000100 %
b0000110110 &
b1110101 (
b0001110101 +
1,
#401
0,
#402
b0000000000000011 %
b0000110101 &
b1101010 (
b0001101010 +
1,
#403
0,
#404
b0000000000000010 %
b0000110100 &
b1010101 (
b0001010101 +
1,
#405
0,
#406
b0000000000000001 %
b0000110011 &
b0101011 (
b0000101011 +
1,
#407
0,
#408
b0000000000000000 %
b0000110010 &
b1010110 (
b0001010110 +
1,
#409
0,
#410
1$
b0000000000011100 %
b0000110001 &
b0101100 (
b0000101100 +
1,
11
b00000000000000000000000000000100 3
#411
0,
#412
0$
b0000000000011011 %
b0000110000 &
b1011001 (
b0001011001 +
1,
b00001111 /
01
b00000000000000000000000000000100 2
#413
0,
#414
b0000000000011010 %
b0000101111 &
b0110011 (
b0000110011 +
1,
#415
0,
#416
b0000000000011001 %
b0000101110 &
b1100110 (
b0001100110 +
1,
#417
0,
#418
b0000000000011000 %
b0000101101 &
b1001101 (
b0001001101 +
1,
#419
0,
#420
b0000000000010111 %
b0000101100 &
b0011011 (
b0000011011 +
1,
#421
0,
#422
b0000000000010110 %
b0000101011 &
b0110111 (
b0000110111 +
1,
#423
0,
#424
b0000000000010101 %
b0000101010 &
b1101110 (
b0001101110 +
1,
#425
0,
#426
b0000000000010100 %
b0000101001 &
b1011101 (
b0001011101 +
1,
#427
0,
#428
b0000000000010011 %
b0000101000 &
b0111011 (
b0000111011 +
1,
#429
0,
#430
b0000000000010010 %
b0000100111 &
b1110110 (
b0001110110 +
1,
#431
0,
#432
b0000000000010001 %
b0000100110 &
b1101101 (
b0001101101 +
1,
#433
0,
#434
b0000000000010000 %
b0000100101 &
b1011010 (
b0001011010 +
1,
#435
0,
#436
b0000000000001111 %
b0000100100 &
b0110100 (
b0000110100 +
1,
#437
0,
#438
b0000000000001110 %
b0000100011 &
b1101001 (
b0001101001 +
1,
#439
0,
#440
b0000000000001101 %
b0000100010 &
b1010010 (
b0001010010 +
1,
#441
0,
#442
b0000000000001100 %
b0000100001 &
b0100100 (
b0000100100 +
1,
#443
0,
#444
b0000000000001011 %
b0000100000 &
b1001001 (
b0001001001 +
1,
#445
0,
#446
b0000000000001010 %
b0000011111 &
b0010011 (
b0000010011 +
1,
#447
0,
#448
b0000000000001001 %
b0000011110 &
b0100111 (
b0000100111 +
1,
#449
0,
#450
b0000000000001000 %
b0000011101 &
b1001110 (
b0001001110 +
1,
#451
0,
#452
b0000000000000111 %
b0000011100 &
b0011100 (
b0000011100 +
1,
#453
0,
#454
b0000000000000110 %
b0000011011 &
b0111000 (
b0000111000 +
1,
#455
0,
#456
b0000000000000101 %
b0000011010 &
b1110001 (
b0001110001 +
1,
#457
0,
#458
b0000000000000100 %
b0000011001 &
b1100010 (
b0001100010 +
1,
#459
0,
#460
b0000000000000011 %
b0000011000 &
b1000101 (
b0001000101 +
1,
#461
0,
#462
b0000000000000010 %
b0000010111 &
b0001011 (
b0000001011 +
1,
#463
0,
#464
b0000000000000001 %
b0000010110 &
b0010111 (
b0000010111 +
1,
#465
0,
#466
b0000000000000000 %
b0000010101 &
b0101111 (
b0000101111 +
1,
#467
0,
#468
1$
b0000000000011100 %
b0000010100 &
b1011110 (
b0001011110 +
1,
11
b00000000000000000000000000000101 3
#469
0,
#470
0$
b0000000000011011 %
b0000010011 &
b0111100 (
b0000111100 +
1,
b00011111 /
01
b00000000000000000000000000000101 2
#471
0,
#472
b0000000000011010 %
b0000010010 &
b1111001 (
b0001111001 +
1,
#473
0,
#474
b0000000000011001 %
b0000010001 &
b1110010 (
b0001110010 +
1,
#475
0,
#476
b0000000000011000 %
b0000010000 &
b1100101 (
b0001100101 +
1,
#477
0,
#478
b0000000000010111 %
b0000001111 &
b1001010 (
b0001001010 +
1,
#479
0,
#480
b0000000000010110 %
b0000001110 &
b0010100 (
b0000010100 +
1,
#481
0,
#482
b0000000000010101 %
b0000001101 &
b0101000 (
b0000101000 +
1,
#483
0,
