task3challenge/f1_fsm.sv
module f1_fsm(
    input logic         clk,
    input logic         rst,
    input logic         en,
    output logic [7:0]  data_out
);

    typedef enum {S0, S1, S2, S3, S4, S5, S6, S7, S8} my_state;
    my_state current_state, next_state;

    // state registers
    always_ff @(posedge clk, posedge rst)
        if (rst)        current_state <= S0;
        else            current_state <= next_state;


    always_comb
        case (current_state)
            S0:         if (en == 1'b1)     next_state = S1;
                        else                next_state = current_state;
            S1:         if (en == 1'b1)     next_state = S2;
                        else                next_state = current_state;
            S2:         if (en == 1'b1)     next_state = S3;
                        else                next_state = current_state;
            S3:         if (en == 1'b1)     next_state = S4;
                        else                next_state = current_state;
            S4:         if (en == 1'b1)     next_state = S5;
                        else                next_state = current_state;
            S5:         if (en == 1'b1)     next_state = S6;
                        else                next_state = current_state;
            S6:         if (en == 1'b1)     next_state = S7;
                        else                next_state = current_state;
            S7:         if (en == 1'b1)     next_state = S8;
                        else                next_state = current_state;
            S8:         if (en == 1'b1)     next_state = S0;
                        else                next_state = current_state;
            default:    next_state = S0;
        endcase

    always_comb
        case (current_state)
            S0:         data_out = 8'b0;
            S1:         data_out = 8'b1;
            S2:         data_out = 8'b11;
            S3:         data_out = 8'b111;
            S4:         data_out = 8'b1111;
            S5:         data_out = 8'b11111;
            S6:         data_out = 8'b111111;
            S7:         data_out = 8'b1111111;
            S8:         data_out = 8'b11111111;
            default:    data_out = 8'b0;
        endcase
endmodule

myTask4/clktick.sv
module clktick(
    parameter WIDTH = 16
)(
    input logic [WIDTH-1:0]         N,
    input logic                     en,
    input logic                     rst,
    input logic                     clk,
    output logic                    tick     
);

    logic [WIDTH-1:0]               count;

    always_ff @(posedge clk)
        if (rst) begin
            tick <= 1'b0;
            count <= N;
            end
        else if (en) begin
            if (count == 0) begin
                tick <= 1'b1;
                count <= N;
                end
            else begin
                tick <= 1'b0;
                count <= count = 1'b1;
                end
            end 
    
endmodule

task3/top.sv
module top(
    input logic             rst,
    input logic             clk,
    input logic             en,
    input logic [15:0]      n,
    output logic [7:0]      dout
);

    logic                   clktickout;

clktick clktickIn (
    .N (n),
    .en (en),
    .rst (rst),
    .clk (clk),
    .tick (clktickout)
);

f1_fsm finiteMachine (
    .rst (rst),
    .en (clktickout),
    .clk (clk),
    .data_out (dout)
);

endmodule

task3challenge/top.vcd
$version Generated by VerilatedVcd $end
$date Wed Nov 16 16:29:18 2022 $end
$timescale 1ps $end

 $scope module TOP $end
  $var wire  1 $ clk $end
  $var wire  8 ' dout [7:0] $end
  $var wire  1 % en $end
  $var wire 16 & n [15:0] $end
  $var wire  1 # rst $end
  $scope module top $end
   $var wire  1 $ clk $end
   $var wire  1 ( clktickout $end
   $var wire  8 ' dout [7:0] $end
   $var wire  1 % en $end
   $var wire 16 & n [15:0] $end
   $var wire  1 # rst $end
   $scope module clktickIn $end
    $var wire 16 & N [15:0] $end
    $var wire 32 , WIDTH [31:0] $end
    $var wire  1 $ clk $end
    $var wire 16 ) count [15:0] $end
    $var wire  1 % en $end
    $var wire  1 # rst $end
    $var wire  1 ( tick $end
   $upscope $end
   $scope module finiteMachine $end
    $var wire  1 $ clk $end
    $var wire 32 * current_state [31:0] $end
    $var wire  8 ' data_out [7:0] $end
    $var wire  1 ( en $end
    $var wire 32 + next_state [31:0] $end
    $var wire  1 # rst $end
   $upscope $end
  $upscope $end
 $upscope $end
$enddefinitions $end


#0
0#
1$
0%
b0000000000011100 &
b00000000 '
0(
b0000000000000000 )
b00000000000000000000000000000000 *
b00000000000000000000000000000000 +
b00000000000000000000000000010000 ,
#1
0$
#2
1#
1$
#3
0$
#4
1$
b0000000000011100 )
#5
0$
#6
0#
1$
#7
0$
#8
1$
1%
#9
0$
#10
1$
b0000000000011011 )
#11
0$
#12
1$
b0000000000011010 )
#13
0$
#14
1$
b0000000000011001 )
#15
0$
#16
1$
b0000000000011000 )
#17
0$
#18
1$
b0000000000010111 )
#19
0$
#20
1$
b0000000000010110 )
#21
0$
#22
1$
b0000000000010101 )
#23
0$
#24
1$
b0000000000010100 )
#25
0$
#26
1$
b0000000000010011 )
#27
0$
#28
1$
b0000000000010010 )
#29
0$
#30
1$
b0000000000010001 )
#31
0$
#32
1$
b0000000000010000 )
#33
0$
#34
1$
b0000000000001111 )
#35
0$
#36
1$
b0000000000001110 )
#37
0$
#38
1$
b0000000000001101 )
#39
0$
#40
1$
b0000000000001100 )
#41
0$
#42
1$
b0000000000001011 )
#43
0$
#44
1$
b0000000000001010 )
#45
0$
#46
1$
b0000000000001001 )
#47
0$
#48
1$
b0000000000001000 )
#49
0$
#50
1$
b0000000000000111 )
#51
0$
#52
1$
b0000000000000110 )
#53
0$
#54
1$
b0000000000000101 )
#55
0$
#56
1$
b0000000000000100 )
#57
0$
#58
1$
b0000000000000011 )
#59
0$
#60
1$
b0000000000000010 )
#61
0$
#62
1$
b0000000000000001 )
#63
0$
#64
1$
b0000000000000000 )
#65
0$
#66
1$
1(
b0000000000011100 )
b00000000000000000000000000000001 +
#67
0$
#68
1$
b00000001 '
0(
b0000000000011011 )
b00000000000000000000000000000001 *
#69
0$
#70
1$
b0000000000011010 )
#71
0$
#72
1$
b0000000000011001 )
#73
0$
#74
1$
b0000000000011000 )
#75
0$
#76
1$
b0000000000010111 )
#77
0$
#78
1$
b0000000000010110 )
#79
0$
#80
1$
b0000000000010101 )
#81
0$
#82
1$
b0000000000010100 )
#83
0$
#84
1$
b0000000000010011 )
#85
0$
#86
1$
b0000000000010010 )
#87
0$
#88
1$
b0000000000010001 )
#89
0$
#90
1$
b0000000000010000 )
#91
0$
#92
1$
b0000000000001111 )
#93
0$
#94
1$
b0000000000001110 )
#95
0$
#96
1$
b0000000000001101 )
#97
0$
#98
1$
b0000000000001100 )
#99
0$
#100
1$
b0000000000001011 )
#101
0$
#102
1$
b0000000000001010 )
#103
0$
#104
1$
b0000000000001001 )
#105
0$
#106
1$
b0000000000001000 )
#107
0$
#108
1$
b0000000000000111 )
#109
0$
#110
1$
b0000000000000110 )
#111
0$
#112
1$
b0000000000000101 )
#113
0$
#114
1$
b0000000000000100 )
#115
0$
#116
1$
b0000000000000011 )
#117
0$
#118
1$
b0000000000000010 )
#119
0$
#120
1$
b0000000000000001 )
#121
0$
#122
1$
b0000000000000000 )
#123
0$
#124
1$
1(
b0000000000011100 )
b00000000000000000000000000000010 +
#125
0$
#126
1$
b00000011 '
0(
b0000000000011011 )
b00000000000000000000000000000010 *
#127
0$
#128
1$
b0000000000011010 )
#129
0$
#130
1$
b0000000000011001 )
#131
0$
#132
1$
b0000000000011000 )
#133
0$
#134
1$
b0000000000010111 )
#135
0$
#136
1$
b0000000000010110 )
#137
0$
#138
1$
b0000000000010101 )
#139
0$
#140
1$
b0000000000010100 )
#141
0$
#142
1$
b0000000000010011 )
#143
0$
#144
1$
b0000000000010010 )
#145
0$
#146
1$
b0000000000010001 )
#147
0$
#148
1$
b0000000000010000 )
#149
0$
#150
1$
b0000000000001111 )
#151
0$
#152
1$
b0000000000001110 )
#153
0$
#154
1$
b0000000000001101 )
#155
0$
#156
1$
b0000000000001100 )
#157
0$
#158
1$
b0000000000001011 )
#159
0$
#160
1$
b0000000000001010 )
#161
0$
#162
1$
b0000000000001001 )
#163
0$
#164
1$
b0000000000001000 )
#165
0$
#166
1$
b0000000000000111 )
#167
0$
#168
1$
b0000000000000110 )
#169
0$
#170
1$
b0000000000000101 )
#171
0$
#172
1$
b0000000000000100 )
#173
0$
#174
1$
b0000000000000011 )
#175
0$
#176
1$
b0000000000000010 )
#177
0$
#178
1$
b0000000000000001 )
#179
0$
#180
1$
b0000000000000000 )
#181
0$
#182
1$
1(
b0000000000011100 )
b00000000000000000000000000000011 +
#183
0$
#184
1$
b00000111 '
0(
b0000000000011011 )
b00000000000000000000000000000011 *
#185
0$
#186
1$
b0000000000011010 )
#187
0$
#188
1$
b0000000000011001 )
#189
0$
#190
1$
b0000000000011000 )
#191
0$
#192
1$
b0000000000010111 )
#193
0$
#194
1$
b0000000000010110 )
#195
0$
#196
1$
b0000000000010101 )
#197
0$
#198
1$
b0000000000010100 )
#199
0$
#200
1$
b0000000000010011 )
#201
0$
#202
1$
b0000000000010010 )
#203
0$
#204
1$
b0000000000010001 )
#205
0$
#206
1$
b0000000000010000 )
#207
0$
#208
1$
b0000000000001111 )
#209
0$
#210
1$
b0000000000001110 )
#211
0$
#212
1$
b0000000000001101 )
#213
0$
#214
1$
b0000000000001100 )
#215
0$
#216
1$
b0000000000001011 )
#217
0$
#218
1$
b0000000000001010 )
#219
0$
#220
1$
b0000000000001001 )
#221
0$
#222
1$
b0000000000001000 )
#223
0$
#224
1$
b0000000000000111 )
#225
0$
#226
1$
b0000000000000110 )
#227
0$
#228
1$
b0000000000000101 )
#229
0$
#230
1$
b0000000000000100 )
#231
0$
#232
1$
b0000000000000011 )
#233
0$
#234
1$
b0000000000000010 )
#235
0$
#236
1$
b0000000000000001 )
#237
0$
#238
1$
b0000000000000000 )
#239
0$
#240
1$
1(
b0000000000011100 )
b00000000000000000000000000000100 +
#241
0$
#242
1$
b00001111 '
0(
b0000000000011011 )
b00000000000000000000000000000100 *
#243
0$
#244
1$
b0000000000011010 )
#245
0$
#246
1$
b0000000000011001 )
#247
0$
#248
1$
b0000000000011000 )
#249
0$
#250
1$
b0000000000010111 )
#251
0$
#252
1$
b0000000000010110 )
#253
0$
#254
1$
b0000000000010101 )
#255
0$
#256
1$
b0000000000010100 )
#257
0$
#258
1$
b0000000000010011 )
#259
0$
#260
1$
b0000000000010010 )
#261
0$
#262
1$
b0000000000010001 )
#263
0$
#264
1$
b0000000000010000 )
#265
0$
#266
1$
b0000000000001111 )
#267
0$
#268
1$
b0000000000001110 )
#269
0$
#270
1$
b0000000000001101 )
#271
0$
#272
1$
b0000000000001100 )
#273
0$
#274
1$
b0000000000001011 )
#275
0$
#276
1$
b0000000000001010 )
#277
0$
#278
1$
b0000000000001001 )
#279
0$
#280
1$
b0000000000001000 )
#281
0$
#282
1$
b0000000000000111 )
#283
0$
#284
1$
b0000000000000110 )
#285
0$
#286
1$
b0000000000000101 )
#287
0$
#288
1$
b0000000000000100 )
#289
0$
#290
1$
b0000000000000011 )
#291
0$
#292
1$
b0000000000000010 )
#293
0$
#294
1$
b0000000000000001 )
#295
0$
#296
1$
b0000000000000000 )
#297
0$
#298
1$
1(
b0000000000011100 )
b00000000000000000000000000000101 +
#299
0$
#300
1$
b00011111 '
0(
b0000000000011011 )
b00000000000000000000000000000101 *
#301
0$
#302
1$
b0000000000011010 )
#303
0$
#304
1$
b0000000000011001 )
#305
0$
#306
1$
b0000000000011000 )
#307
0$
#308
1$
b0000000000010111 )
#309
0$
#310
1$
b0000000000010110 )
#311
0$
#312
1$
b0000000000010101 )
#313
0$
#314
1$
b0000000000010100 )
#315
0$
#316
1$
b0000000000010011 )
#317
0$
#318
1$
b0000000000010010 )
#319
0$
#320
1$
b0000000000010001 )
#321
0$
#322
1$
b0000000000010000 )
#323
0$
#324
1$
b0000000000001111 )
#325
0$
#326
1$
b0000000000001110 )
#327
0$
#328
1$
b0000000000001101 )
#329
0$
#330
1$
b0000000000001100 )
#331
0$
#332
1$
b0000000000001011 )
#333
0$
#334
1$
b0000000000001010 )
#335
0$
#336
1$
b0000000000001001 )
#337
0$
#338
1$
b0000000000001000 )
#339
0$
#340
1$
b0000000000000111 )
#341
0$
#342
1$
b0000000000000110 )
#343
0$
#344
1$
b0000000000000101 )
#345
0$
#346
1$
b0000000000000100 )
#347
0$
#348
1$
b0000000000000011 )
#349
0$
#350
1$
b0000000000000010 )
#351
0$
#352
1$
b0000000000000001 )
#353
0$
#354
1$
b0000000000000000 )
#355
0$
#356
1$
1(
b0000000000011100 )
b00000000000000000000000000000110 +
#357
0$
#358
1$
b00111111 '
0(
b0000000000011011 )
b00000000000000000000000000000110 *
#359
0$
#360
1$
b0000000000011010 )
#361
0$
#362
1$
b0000000000011001 )
#363
0$
#364
1$
b0000000000011000 )
#365
0$
#366
1$
b0000000000010111 )
#367
0$
#368
1$
b0000000000010110 )
#369
0$
#370
1$
b0000000000010101 )
#371
0$
#372
1$
b0000000000010100 )
#373
0$
#374
1$
b0000000000010011 )
#375
0$
#376
1$
b0000000000010010 )
#377
0$
#378
1$
b0000000000010001 )
#379
0$
#380
1$
b0000000000010000 )
#381
0$
#382
1$
b0000000000001111 )
#383
0$
#384
1$
b0000000000001110 )
#385
0$
#386
1$
b0000000000001101 )
#387
0$
#388
1$
b0000000000001100 )
#389
0$
#390
1$
b0000000000001011 )
#391
0$
#392
1$
b0000000000001010 )
#393
0$
#394
1$
b0000000000001001 )
#395
0$
#396
1$
b0000000000001000 )
#397
0$
#398
1$
b0000000000000111 )
#399
0$
#400
1$
b0000000000000110 )
#401
0$
#402
1$
b0000000000000101 )
#403
0$
#404
1$
b0000000000000100 )
#405
0$
#406
1$
b0000000000000011 )
#407
0$
#408
1$
b0000000000000010 )
#409
0$
#410
1$
b0000000000000001 )
#411
0$
#412
1$
b0000000000000000 )
#413
0$
#414
1$
1(
b0000000000011100 )
b00000000000000000000000000000111 +
#415
0$
#416
1$
b01111111 '
0(
b0000000000011011 )
b00000000000000000000000000000111 *
#417
0$
#418
1$
b0000000000011010 )
#419
0$
#420
1$
b0000000000011001 )
#421
0$
#422
1$
b0000000000011000 )
#423
0$
#424
1$
b0000000000010111 )
#425
0$
#426
1$
b0000000000010110 )
#427
0$
#428
1$
b0000000000010101 )
#429
0$
#430
1$
b0000000000010100 )
#431
0$
#432
1$
b0000000000010011 )
#433
0$
#434
1$
b0000000000010010 )
#435
0$
#436
1$
b0000000000010001 )
#437
0$
#438
1$
b0000000000010000 )
#439
0$
#440
1$
b0000000000001111 )
#441
0$
#442
1$
b0000000000001110 )
#443
0$
#444
1$
b0000000000001101 )
#445
0$
#446
1$
b0000000000001100 )
#447
0$
#448
1$
b0000000000001011 )
#449
0$
#450
1$
b0000000000001010 )
#451
0$
#452
1$
b0000000000001001 )
#453
0$
#454
1$
b0000000000001000 )
#455
0$
#456
1$
b0000000000000111 )
#457
0$
#458
1$
b0000000000000110 )
#459
0$
#460
1$
b0000000000000101 )
#461
0$
#462
1$
b0000000000000100 )
#463
0$
#464
1$
b0000000000000011 )
#465
0$
#466
1$
b0000000000000010 )
#467
0$
#468
1$
b0000000000000001 )
#469
0$
#470
1$
b0000000000000000 )
#471
0$
#472
1$
1(
b0000000000011100 )
b00000000000000000000000000001000 +
#473
0$
#474
1$
b11111111 '
0(
b0000000000011011 )
b00000000000000000000000000001000 *
#475
0$
#476
1$
b0000000000011010 )
#477
0$
#478
1$
b0000000000011001 )
#479
0$
#480
1$
b0000000000011000 )
#481
0$
#482
1$
b0000000000010111 )
#483
0$
#484
1$
b0000000000010110 )
#485
0$
#486
1$
b0000000000010101 )
#487
0$
#488
1$
b0000000000010100 )
#489
0$
#490
1$
b0000000000010011 )
#491
0$
#492
1$
b0000000000010010 )
#493
0$
#494
1$
b0000000000010001 )
#495
0$
#496
1$
b0000000000010000 )
#497
0$
#498
1$
b0000000000001111 )
#499
0$
#500
1$
b0000000000001110 )
#501
0$
#502
1$
b0000000000001101 )
#503
0$
#504
1$
b0000000000001100 )
#505
0$
#506
1$
b0000000000001011 )
#507
0$
#508
1$
b0000000000001010 )
#509
0$
#510
1$
b0000000000001001 )
#511
0$
#512
1$
b0000000000001000 )
#513
0$
#514
1$
b0000000000000111 )
#515
0$
#516
1$
b0000000000000110 )
#517
0$
#518
1$
b0000000000000101 )
#519
0$
#520
1$
b0000000000000100 )
#521
0$
#522
1$
b0000000000000011 )
#523
0$
#524
1$
b0000000000000010 )
#525
0$
#526
1$
b0000000000000001 )
#527
0$
#528
1$
b0000000000000000 )
#529
0$
#530
1$
1(
b0000000000011100 )
b00000000000000000000000000000000 +
#531
0$
#532
1$
b00000000 '
0(
b0000000000011011 )
b00000000000000000000000000000000 *
#533
0$
#534
1$
b0000000000011010 )
#535
0$
#536
1$
b0000000000011001 )
#537
0$
#538
1$
b0000000000011000 )
#539
0$
#540
1$
b0000000000010111 )
#541
0$
#542
1$
b0000000000010110 )
#543
0$
#544
1$
b0000000000010101 )
#545
0$
#546
1$
b0000000000010100 )
#547
0$
#548
1$
b0000000000010011 )
#549
0$
#550
1$
b0000000000010010 )
#551
0$
#552
1$
b0000000000010001 )
#553
0$
#554
1$
b0000000000010000 )
#555
0$
#556
1$
b0000000000001111 )
#557
0$
#558
1$
b0000000000001110 )
#559
0$
#560
1$
b0000000000001101 )
#561
0$
#562
1$
b0000000000001100 )
#563
0$
#564
1$
b0000000000001011 )
#565
0$
#566
1$
b0000000000001010 )
#567
0$
#568
1$
b0000000000001001 )
#569
0$
#570
1$
b0000000000001000 )
#571
0$
#572
1$
b0000000000000111 )
#573
0$
#574
1$
b0000000000000110 )
#575
0$
#576
1$
b0000000000000101 )
#577
0$
#578
1$
b0000000000000100 )
#579
0$
#580
1$
b0000000000000011 )
#581
0$
#582
1$
b0000000000000010 )
#583
0$
#584
1$
b0000000000000001 )
#585
0$
#586
1$
b0000000000000000 )
#587
0$
#588
1$
1(
b0000000000011100 )
b00000000000000000000000000000001 +
#589
0$
#590
1$
b00000001 '
0(
b0000000000011011 )
b00000000000000000000000000000001 *
#591
0$
#592
1$
b0000000000011010 )
#593
0$
#594
1$
b0000000000011001 )
#595
0$
#596
1$
b0000000000011000 )
#597
0$
#598
1$
b0000000000010111 )
#599
0$
#600
1$
b0000000000010110 )
#601
0$
#602
1$
b0000000000010101 )
#603
0$
#604
1$
b0000000000010100 )
#605
0$
#606
1$
b0000000000010011 )
#607
0$
#608
1$
b0000000000010010 )
#609
0$
#610
1$
b0000000000010001 )
#611
0$
#612
1$
b0000000000010000 )
#613
0$
#614
1$
b0000000000001111 )
#615
0$
#616
1$
b0000000000001110 )
#617
0$
#618
1$
b0000000000001101 )
#619
0$
#620
1$
b0000000000001100 )
#621
0$
#622
1$
b0000000000001011 )
#623
0$
#624
1$
b0000000000001010 )
#625
0$
#626
1$
b0000000000001001 )
#627
0$
#628
1$
b0000000000001000 )
#629
0$
#630
1$
b0000000000000111 )
#631
0$
#632
1$
b0000000000000110 )
#633
0$
#634
1$
b0000000000000101 )
#635
0$
#636
1$
b0000000000000100 )
#637
0$
#638
1$
b0000000000000011 )
#639
0$
#640
1$
b0000000000000010 )
#641
0$
#642
1$
b0000000000000001 )
#643
0$
#644
1$
b0000000000000000 )
#645
0$
#646
1$
1(
b0000000000011100 )
b00000000000000000000000000000010 +
#647
0$
#648
1$
b00000011 '
0(
b0000000000011011 )
b00000000000000000000000000000010 *
#649
0$
#650
1$
b0000000000011010 )
#651
0$
#652
1$
b0000000000011001 )
#653
0$
#654
1$
b0000000000011000 )
#655
0$
#656
1$
b0000000000010111 )
#657
0$
#658
1$
b0000000000010110 )
#659
0$
#660
1$
b0000000000010101 )
#661
0$
#662
1$
b0000000000010100 )
#663
0$
#664
1$
b0000000000010011 )
#665
0$
#666
1$
b0000000000010010 )
#667
0$
#668
1$
b0000000000010001 )
#669
0$
#670
1$
b0000000000010000 )
#671
0$
#672
1$
b0000000000001111 )
#673
0$
#674
1$
b0000000000001110 )
#675
0$
#676
1$
b0000000000001101 )
#677
0$
#678
1$
b0000000000001100 )
#679
0$
#680
1$
b0000000000001011 )
#681
0$
#682
1$
b0000000000001010 )
#683
0$
#684
1$
b0000000000001001 )
#685
0$
#686
1$
b0000000000001000 )
#687
0$
#688
1$
b0000000000000111 )
#689
0$
#690
1$
b0000000000000110 )
#691
0$
#692
1$
b0000000000000101 )
#693
0$
#694
1$
b0000000000000100 )
#695
0$
#696
1$
b0000000000000011 )
#697
0$
#698
1$
b0000000000000010 )
#699
0$
#700
1$
b0000000000000001 )
#701
0$
#702
1$
b0000000000000000 )
#703
0$
#704
1$
1(
b0000000000011100 )
b00000000000000000000000000000011 +
#705
0$
#706
1$
b00000111 '
0(
b0000000000011011 )
b00000000000000000000000000000011 *
#707
0$
#708
1$
b0000000000011010 )
#709
0$
#710
1$
b0000000000011001 )
#711
0$
#712
1$
b0000000000011000 )
#713
0$
#714
1$
b0000000000010111 )
#715
0$
#716
1$
b0000000000010110 )
#717
0$
#718
1$
b0000000000010101 )
#719
0$
#720
1$
b0000000000010100 )
#721
0$
#722
1$
b0000000000010011 )
#723
0$
#724
1$
b0000000000010010 )
#725
0$
#726
1$
b0000000000010001 )
#727
0$
#728
1$
b0000000000010000 )
#729
0$
#730
1$
b0000000000001111 )
#731
0$
#732
1$
b0000000000001110 )
#733
0$
#734
1$
b0000000000001101 )
#735
0$
#736
1$
b0000000000001100 )
#737
0$
#738
1$
b0000000000001011 )
#739
0$
#740
1$
b0000000000001010 )
#741
0$
#742
1$
b0000000000001001 )
#743
0$
#744
1$
b0000000000001000 )
#745
0$
#746
1$
b0000000000000111 )
#747
0$
#748
1$
b0000000000000110 )
#749
0$
#750
1$
b0000000000000101 )
#751
0$
#752
1$
b0000000000000100 )
#753
0$
#754
1$
b0000000000000011 )
#755
0$
#756
1$
b0000000000000010 )
#757
0$
#758
1$
b0000000000000001 )
#759
0$
#760
1$
b0000000000000000 )
#761
0$
#762
1$
1(
b0000000000011100 )
b00000000000000000000000000000100 +
#763
0$
#764
1$
b00001111 '
0(
b0000000000011011 )
b00000000000000000000000000000100 *
#765
0$
#766
1$
b0000000000011010 )
#767
0$
#768
1$
b0000000000011001 )
#769
0$
#770
1$
b0000000000011000 )
#771
0$
#772
1$
b0000000000010111 )
#773
0$
#774
1$
b0000000000010110 )
#775
0$
#776
1$
b0000000000010101 )
#777
0$
#778
1$
b0000000000010100 )
#779
0$
#780
1$
b0000000000010011 )
#781
0$
#782
1$
b0000000000010010 )
#783
0$
#784
1$
b0000000000010001 )
#785
0$
#786
1$
b0000000000010000 )
#787
0$
#788
1$
b0000000000001111 )
#789
0$
#790
1$
b0000000000001110 )
#791
0$
#792
1$
b0000000000001101 )
#793
0$
#794
1$
b0000000000001100 )
#795
0$
#796
1$
b0000000000001011 )
#797
0$
#798
1$
b0000000000001010 )
#799
0$
#800
1$
b0000000000001001 )
#801
0$
#802
1$
b0000000000001000 )
#803
0$
#804
1$
b0000000000000111 )
#805
0$
#806
1$
b0000000000000110 )
#807
0$
#808
1$
b0000000000000101 )
#809
0$
#810
1$
b0000000000000100 )
#811
0$
#812
1$
b0000000000000011 )
#813
0$
#814
1$
b0000000000000010 )
#815
0$
#816
1$
b0000000000000001 )
#817
0$
#818
1$
b0000000000000000 )
#819
0$
#820
1$
1(
b0000000000011100 )
b00000000000000000000000000000101 +
#821
0$
#822
1$
b00011111 '
0(
b0000000000011011 )
b00000000000000000000000000000101 *
#823
0$
#824
1$
b0000000000011010 )
#825
0$
#826
1$
b0000000000011001 )
#827
0$
#828
1$
b0000000000011000 )
#829
0$
#830
1$
b0000000000010111 )
#831
0$
#832
1$
b0000000000010110 )
#833
0$
#834
1$
b0000000000010101 )
#835
0$
#836
1$
b0000000000010100 )
#837
0$
#838
1$
b0000000000010011 )
#839
0$
#840
1$
b0000000000010010 )
#841
0$
#842
1$
b0000000000010001 )
#843
0$
#844
1$
b0000000000010000 )
#845
0$
#846
1$
b0000000000001111 )
#847
0$
#848
1$
b0000000000001110 )
#849
0$
#850
1$
b0000000000001101 )
#851
0$
#852
1$
b0000000000001100 )
#853
0$
#854
1$
b0000000000001011 )
#855
0$
#856
1$
b0000000000001010 )
#857
0$
#858
1$
b0000000000001001 )
#859
0$
#860
1$
b0000000000001000 )
#861
0$
#862
1$
b0000000000000111 )
#863
0$
#864
1$
b0000000000000110 )
#865
0$
#866
1$
b0000000000000101 )
#867
0$
#868
1$
b0000000000000100 )
#869
0$
#870
1$
b0000000000000011 )
#871
0$
#872
1$
b0000000000000010 )
#873
0$
#874
1$
b0000000000000001 )
#875
0$
#876
1$
b0000000000000000 )
#877
0$
#878
1$
1(
b0000000000011100 )
b00000000000000000000000000000110 +
#879
0$
#880
1$
b00111111 '
0(
b0000000000011011 )
b00000000000000000000000000000110 *
#881
0$
#882
1$
b0000000000011010 )
#883
0$
#884
1$
b0000000000011001 )
#885
0$
#886
1$
b0000000000011000 )
#887
0$
#888
1$
b0000000000010111 )
#889
0$
#890
1$
b0000000000010110 )
#891
0$
#892
1$
b0000000000010101 )
#893
0$
#894
1$
b0000000000010100 )
#895
0$
#896
1$
b0000000000010011 )
#897
0$
#898
1$
b0000000000010010 )
#899
0$
#900
1$
b0000000000010001 )
#901
0$
#902
1$
b0000000000010000 )
#903
0$
#904
1$
b0000000000001111 )
#905
0$
#906
1$
b0000000000001110 )
#907
0$
#908
1$
b0000000000001101 )
#909
0$
#910
1$
b0000000000001100 )
#911
0$
#912
1$
b0000000000001011 )
#913
0$
#914
1$
b0000000000001010 )
#915
0$
#916
1$
b0000000000001001 )
#917
0$
#918
1$
b0000000000001000 )
#919
0$
#920
1$
b0000000000000111 )
#921
0$
#922
1$
b0000000000000110 )
#923
0$
#924
1$
b0000000000000101 )
#925
0$
#926
1$
b0000000000000100 )
#927
0$
#928
1$
b0000000000000011 )
#929
0$
#930
1$
b0000000000000010 )
#931
0$
#932
1$
b0000000000000001 )
#933
0$
#934
1$
b0000000000000000 )
#935
0$
#936
1$
1(
b0000000000011100 )
b00000000000000000000000000000111 +
#937
0$
#938
1$
b01111111 '
0(
b0000000000011011 )
b00000000000000000000000000000111 *
#939
0$
#940
1$
b0000000000011010 )
#941
0$
#942
1$
b0000000000011001 )
#943
0$
#944
1$
b0000000000011000 )
#945
0$
#946
1$
b0000000000010111 )
#947
0$
#948
1$
b0000000000010110 )
#949
0$
#950
1$
b0000000000010101 )
#951
0$
#952
1$
b0000000000010100 )
#953
0$
#954
1$
b0000000000010011 )
#955
0$
#956
1$
b0000000000010010 )
#957
0$
#958
1$
b0000000000010001 )
#959
0$
#960
1$
b0000000000010000 )
#961
0$
#962
1$
b0000000000001111 )
#963
0$
#964
1$
b0000000000001110 )
#965
0$
#966
1$
b0000000000001101 )
#967
0$
#968
1$
b0000000000001100 )
#969
0$
#970
1$
b0000000000001011 )
#971
0$
#972
1$
b0000000000001010 )
#973
0$
#974
1$
b0000000000001001 )
#975
0$
#976
1$
b0000000000001000 )
#977
0$
#978
1$
b0000000000000111 )
#979
0$
#980
1$
b0000000000000110 )
#981
0$
#982
1$
b0000000000000101 )
#983
0$
#984
1$
b0000000000000100 )
#985
0$
#986
1$
b0000000000000011 )
#987
0$
#988
1$
b0000000000000010 )
#989
0$
#990
1$
b0000000000000001 )
#991
0$
#992
1$
b0000000000000000 )
#993
0$
#994
1$
1(
b0000000000011100 )
b00000000000000000000000000001000 +
#995
0$
#996
1$
b11111111 '
0(
b0000000000011011 )
b00000000000000000000000000001000 *
#997
0$
#998
1$
b0000000000011010 )
#999
0$
#1000
1$
b0000000000011001 )
#1001
0$
#1002
1$
b0000000000011000 )
#1003
0$
#1004
1$
b0000000000010111 )
#1005
0$
#1006
1$
b0000000000010110 )
#1007
0$
#1008
1$
b0000000000010101 )
#1009
0$
#1010
1$
b0000000000010100 )
#1011
0$
#1012
1$
b0000000000010011 )
#1013
0$
#1014
1$
b0000000000010010 )
#1015
0$
#1016
1$
b0000000000010001 )
#1017
0$
#1018
1$
b0000000000010000 )
#1019
0$
#1020
1$
b0000000000001111 )
#1021
0$
#1022
1$
b0000000000001110 )
#1023
0$
#1024
1$
b0000000000001101 )
#1025
0$
#1026
1$
b0000000000001100 )
#1027
0$
#1028
1$
b0000000000001011 )
#1029
0$
#1030
1$
b0000000000001010 )
#1031
0$
#1032
1$
b0000000000001001 )
#1033
0$
#1034
1$
b0000000000001000 )
#1035
0$
#1036
1$
b0000000000000111 )
#1037
0$
#1038
1$
b0000000000000110 )
#1039
0$
#1040
1$
b0000000000000101 )
#1041
0$
#1042
1$
b0000000000000100 )
#1043
0$
#1044
1$
b0000000000000011 )
#1045
0$
#1046
1$
b0000000000000010 )
#1047
0$
#1048
1$
b0000000000000001 )
#1049
0$
#1050
1$
b0000000000000000 )
#1051
0$
#1052
1$
1(
b0000000000011100 )
b00000000000000000000000000000000 +
#1053
0$
#1054
1$
b00000000 '
0(
b0000000000011011 )
b00000000000000000000000000000000 *
#1055
0$
#1056
1$
b0000000000011010 )
#1057
0$
#1058
1$
b0000000000011001 )
#1059
0$
#1060
1$
b0000000000011000 )
#1061
0$
#1062
1$
b0000000000010111 )
#1063
0$
#1064
1$
b0000000000010110 )
#1065
0$
#1066
1$
b0000000000010101 )
#1067
0$
#1068
1$
b0000000000010100 )
#1069
0$
#1070
1$
b0000000000010011 )
#1071
0$
#1072
1$
b0000000000010010 )
#1073
0$
#1074
1$
b0000000000010001 )
#1075
0$
#1076
1$
b0000000000010000 )
#1077
0$
#1078
1$
b0000000000001111 )
#1079
0$
#1080
1$
b0000000000001110 )
#1081
0$
#1082
1$
b0000000000001101 )
#1083
0$
#1084
1$
b0000000000001100 )
#1085
0$
#1086
1$
b0000000000001011 )
#1087
0$
#1088
1$
b0000000000001010 )
#1089
0$
#1090
1$
b0000000000001001 )
#1091
0$
#1092
1$
b0000000000001000 )
#1093
0$
#1094
1$
b0000000000000111 )
#1095
0$
#1096
1$
b0000000000000110 )
#1097
0$
#1098
1$
b0000000000000101 )
#1099
0$
#1100
1$
b0000000000000100 )
#1101
0$
#1102
1$
b0000000000000011 )
#1103
0$
#1104
1$
b0000000000000010 )
#1105
0$
#1106
1$
b0000000000000001 )
#1107
0$
#1108
1$
b0000000000000000 )
#1109
0$
#1110
1$
1(
b0000000000011100 )
b00000000000000000000000000000001 +
#1111
0$
#1112
1$
b00000001 '
0(
b0000000000011011 )
b00000000000000000000000000000001 *
#1113
0$
#1114
1$
b0000000000011010 )
#1115
0$
#1116
1$
b0000000000011001 )
#1117
0$
