task1challenge/lfsr.sv
module lfsr #()(
    input logic         rst,
    input logic         en,
    input logic         clk,
    output logic [8:1]  dout
);

logic [8:1]         sreg;

always_ff @ (posedge clk, posedge rst)
    if (rst)
        sreg <= 8'b1;
    else if (en)
        sreg <= {sreg[7:1], sreg[7] ^ sreg[3]};

assign dout = sreg;

endmodule

task1challenge/lfsr.vcd
$version Generated by VerilatedVcd $end
$date Tue Nov  8 21:40:53 2022 $end
$timescale 1ps $end

 $scope module TOP $end
  $var wire  1 % clk $end
  $var wire  8 & dout [8:1] $end
  $var wire  1 $ en $end
  $var wire  1 # rst $end
  $scope module lfsr $end
   $var wire  1 % clk $end
   $var wire  8 & dout [8:1] $end
   $var wire  1 $ en $end
   $var wire  1 # rst $end
   $var wire  8 ' sreg [8:1] $end
  $upscope $end
 $upscope $end
$enddefinitions $end


#0
1#
0$
1%
b00000000 &
b00000000 '
#1
0%
#2
1%
b00000001 &
b00000001 '
#3
0%
#4
1%
#5
0%
#6
0#
1%
#7
0%
#8
1%
#9
0%
#10
1%
#11
0%
#12
1%
#13
0%
#14
1%
#15
0%
#16
1%
#17
0%
#18
1%
#19
0%
#20
1%
#21
0%
#22
1%
#23
0%
#24
1%
#25
0%
#26
1%
#27
0%
#28
1%
#29
0%
#30
1%
#31
0%
#32
1%
#33
0%
#34
1%
#35
0%
#36
1%
#37
0%
#38
1%
#39
0%
#40
1%
#41
0%
#42
1%
#43
0%
#44
1%
#45
0%
#46
1%
#47
0%
#48
1%
#49
0%
#50
1%
#51
0%
#52
1%
#53
0%
#54
1%
#55
0%
#56
1%
#57
0%
#58
1%
#59
0%
#60
1%
#61
0%
#62
1%
#63
0%
#64
1%
#65
0%
#66
1%
#67
0%
#68
1%
#69
0%
#70
1%
#71
0%
#72
1%
#73
0%
#74
1%
#75
0%
#76
1%
#77
0%
#78
1%
#79
0%
#80
1%
#81
0%
#82
1%
#83
0%
#84
1%
#85
0%
#86
1%
#87
0%
#88
1%
#89
0%
#90
1%
#91
0%
#92
1%
#93
0%
#94
1%
#95
0%
#96
1%
#97
0%
#98
1%
#99
0%
#100
1%
#101
0%
#102
1%
#103
0%
#104
1%
#105
0%
#106
1%
#107
0%
#108
1%
#109
0%
#110
1%
#111
0%
#112
1%
#113
0%
#114
1%
#115
0%
#116
1%
#117
0%
#118
1%
#119
0%
#120
1%
#121
0%
#122
1%
#123
0%
#124
1%
#125
0%
#126
1%
#127
0%
#128
1%
#129
0%
#130
1%
#131
0%
#132
1%
#133
0%
#134
1%
#135
0%
#136
1%
#137
0%
#138
1%
#139
0%
#140
1%
#141
0%
#142
1%
#143
0%
#144
1%
#145
0%
#146
1%
#147
0%
#148
1%
#149
0%
#150
1%
#151
0%
#152
1%
#153
0%
#154
1%
#155
0%
#156
1%
#157
0%
#158
1%
#159
0%
#160
1%
#161
0%
#162
1%
#163
0%
#164
1%
#165
0%
#166
1%
#167
0%
#168
1%
#169
0%
#170
1%
#171
0%
#172
1%
#173
0%
#174
1%
#175
0%
#176
1%
#177
0%
#178
1%
#179
0%
#180
1%
#181
0%
#182
1%
#183
0%
#184
1%
#185
0%
#186
1%
#187
0%
#188
1%
#189
0%
#190
1%
#191
0%
#192
1%
#193
0%
#194
1%
#195
0%
#196
1%
#197
0%
#198
1%
#199
0%
#200
1%
#201
0%
#202
1%
#203
0%
#204
1%
#205
0%
#206
1%
#207
0%
#208
1%
#209
0%
#210
1%
#211
0%
#212
1%
#213
0%
#214
1%
#215
0%
#216
1%
#217
0%
#218
1%
#219
0%
#220
1%
#221
0%
#222
1%
#223
0%
#224
1%
#225
0%
#226
1%
#227
0%
#228
1%
#229
0%
#230
1%
#231
0%
#232
1%
#233
0%
#234
1%
#235
0%
#236
1%
#237
0%
#238
1%
#239
0%
#240
1%
#241
0%
#242
1%
#243
0%
#244
1%
#245
0%
#246
1%
#247
0%
#248
1%
#249
0%
#250
1%
#251
0%
#252
1%
#253
0%
#254
1%
#255
0%
#256
1%
#257
0%
#258
1%
#259
0%
#260
1%
#261
0%
#262
1%
#263
0%
#264
1%
#265
0%
#266
1%
#267
0%
#268
1%
#269
0%
#270
1%
#271
0%
#272
1%
#273
0%
#274
1%
#275
0%
#276
1%
#277
0%
#278
1%
#279
0%
#280
1%
#281
0%
#282
1%
#283
0%
#284
1%
#285
0%
#286
1%
#287
0%
#288
1%
#289
0%
#290
1%
#291
0%
#292
1%
#293
0%
#294
1%
#295
0%
#296
1%
#297
0%
#298
1%
#299
0%
#300
1%
#301
0%
#302
1%
#303
0%
#304
1%
#305
0%
#306
1%
#307
0%
#308
1%
#309
0%
#310
1%
#311
0%
#312
1%
#313
0%
#314
1%
#315
0%
#316
1%
#317
0%
#318
1%
#319
0%
#320
1%
#321
0%
#322
1%
#323
0%
#324
1%
#325
0%
#326
1%
#327
0%
#328
1%
#329
0%
#330
1%
#331
0%
#332
1%
#333
0%
#334
1%
#335
0%
#336
1%
#337
0%
#338
1%
#339
0%
#340
1%
#341
0%
#342
1%
#343
0%
#344
1%
#345
0%
#346
1%
#347
0%
#348
1%
#349
0%
#350
1%
#351
0%
#352
1%
#353
0%
#354
1%
#355
0%
#356
1%
#357
0%
#358
1%
#359
0%
#360
1%
#361
0%
#362
1%
#363
0%
#364
1%
#365
0%
#366
1%
#367
0%
#368
1%
#369
0%
#370
1%
#371
0%
#372
1%
#373
0%
#374
1%
#375
0%
#376
1%
#377
0%
#378
1%
#379
0%
#380
1%
#381
0%
#382
1%
#383
0%
#384
1%
#385
0%
#386
1%
#387
0%
#388
1%
#389
0%
#390
1%
#391
0%
#392
1%
#393
0%
#394
1%
#395
0%
#396
1%
#397
0%
#398
1%
#399
0%
#400
1%
#401
0%
#402
1%
#403
0%
#404
1%
#405
0%
#406
1%
#407
0%
#408
1%
#409
0%
#410
1%
#411
0%
#412
1%
#413
0%
#414
1%
#415
0%
#416
1%
#417
0%
#418
1%
#419
0%
#420
1%
#421
0%
#422
1%
#423
0%
#424
1%
#425
0%
#426
1%
#427
0%
#428
1%
#429
0%
#430
1%
#431
0%
#432
1%
#433
0%
#434
1%
#435
0%
#436
1%
#437
0%
#438
1%
#439
0%
#440
1%
#441
0%
#442
1%
#443
0%
#444
1%
#445
0%
#446
1%
#447
0%
#448
1%
#449
0%
#450
1%
#451
0%
#452
1%
#453
0%
#454
1%
#455
0%
#456
1%
#457
0%
#458
1%
#459
0%
#460
1%
#461
0%
#462
1%
#463
0%
#464
1%
#465
0%
#466
1%
#467
0%
#468
1%
#469
0%
#470
1%
#471
0%
#472
1%
#473
0%
#474
1%
#475
0%
#476
1%
#477
0%
#478
1%
#479
0%
#480
1%
#481
0%
#482
1%
#483
0%
#484
1%
#485
0%
#486
1%
#487
0%
#488
1%
#489
0%
#490
1%
#491
0%
#492
1%
#493
0%
#494
1%
#495
0%
#496
1%
#497
0%
#498
1%
#499
0%
#500
1%
#501
0%
#502
1%
#503
0%
#504
1%
#505
0%
#506
1%
#507
0%
#508
1%
#509
0%
#510
1%
#511
0%
#512
1%
#513
0%
#514
1%
#515
0%
#516
1%
#517
0%
#518
1%
#519
0%
#520
1%
#521
0%
#522
1%
#523
0%
#524
1%
#525
0%
#526
1%
#527
0%
#528
1%
#529
0%
#530
1%
#531
0%
#532
1%
#533
0%
#534
1%
#535
0%
#536
1%
#537
0%
#538
1%
#539
0%
#540
1%
#541
0%
#542
1%
#543
0%
#544
1%
#545
0%
#546
1%
#547
0%
#548
1%
#549
0%
#550
1%
#551
0%
#552
1%
#553
0%
#554
1%
#555
0%
#556
1%
#557
0%
#558
1%
#559
0%
#560
1%
#561
0%
#562
1%
#563
0%
#564
1%
#565
0%
#566
1%
#567
0%
#568
1%
#569
0%
#570
1%
#571
0%
#572
1%
#573
0%
#574
1%
#575
0%
#576
1%
#577
0%
#578
1%
#579
0%
#580
1%
#581
0%
#582
1%
#583
0%
#584
1%
#585
0%
#586
1%
#587
0%
#588
1%
#589
0%
#590
1%
#591
0%
#592
1%
#593
0%
#594
1%
#595
0%
#596
1%
#597
0%
#598
1%
#599
0%
#600
1%
#601
0%
#602
1%
#603
0%
#604
1%
#605
0%
#606
1%
#607
0%
#608
1%
#609
0%
#610
1%
#611
0%
#612
1%
#613
0%
#614
1%
#615
0%
#616
1%
#617
0%
#618
1%
#619
0%
#620
1%
#621
0%
#622
1%
#623
0%
#624
1%
#625
0%
#626
1%
#627
0%
#628
1%
#629
0%
#630
1%
#631
0%
#632
1%
#633
0%
#634
1%
#635
0%
#636
1%
#637
0%
#638
1%
#639
0%
#640
1%
#641
0%
#642
1%
#643
0%
#644
1%
#645
0%
#646
1%
#647
0%
#648
1%
#649
0%
#650
1%
#651
0%
#652
1%
#653
0%
#654
1%
#655
0%
#656
1%
#657
0%
#658
1%
#659
0%
#660
1%
#661
0%
#662
1%
#663
0%
#664
1%
#665
0%
#666
1%
#667
0%
#668
1%
#669
0%
#670
1%
#671
0%
#672
1%
#673
0%
#674
1%
#675
0%
#676
1%
#677
0%
#678
1%
#679
0%
#680
1%
#681
0%
#682
1%
#683
0%
#684
1%
#685
0%
#686
1%
#687
0%
#688
1%
#689
0%
#690
1%
#691
0%
#692
1%
#693
0%
#694
1%
#695
0%
#696
1%
#697
0%
#698
1%
#699
0%
#700
1%
#701
0%
#702
1%
#703
0%
#704
1%
#705
0%
#706
1%
#707
0%
#708
1%
#709
0%
#710
1%
#711
0%
#712
1%
#713
0%
#714
1%
#715
0%
#716
1%
#717
0%
#718
1%
#719
0%
#720
1%
#721
0%
#722
1%
#723
0%
#724
1%
#725
0%
#726
1%
#727
0%
#728
1%
#729
0%
#730
1%
#731
0%
#732
1%
#733
0%
#734
1%
#735
0%
#736
1%
#737
0%
#738
1%
#739
0%
#740
1%
#741
0%
#742
1%
#743
0%
#744
1%
#745
0%
#746
1%
#747
0%
#748
1%
#749
0%
#750
1%
#751
0%
#752
1%
#753
0%
#754
1%
#755
0%
#756
1%
#757
0%
#758
1%
#759
0%
#760
1%
#761
0%
#762
1%
#763
0%
#764
1%
#765
0%
#766
1%
#767
0%
#768
1%
#769
0%
#770
1%
#771
0%
#772
1%
#773
0%
#774
1%
#775
0%
#776
1%
#777
0%
#778
1%
#779
0%
#780
1%
#781
0%
#782
1%
#783
0%
#784
1%
#785
0%
#786
1%
#787
0%
#788
1%
#789
0%
#790
1%
#791
0%
#792
1%
#793
0%
#794
1%
#795
0%
#796
1%
#797
0%
#798
1%
#799
0%
#800
1%
#801
0%
#802
1%
#803
0%
#804
1%
#805
0%
#806
1%
#807
0%
#808
1%
#809
0%
#810
1%
#811
0%
#812
1%
#813
0%
#814
1%
#815
0%
#816
1%
#817
0%
#818
1%
#819
0%
#820
1%
#821
0%
#822
1%
#823
0%
#824
1%
#825
0%
#826
1%
#827
0%
#828
1%
#829
0%
#830
1%
#831
0%
#832
1%
#833
0%
#834
1%
#835
0%
#836
1%
#837
0%
#838
1%
#839
0%
#840
1%
#841
0%
#842
1%
#843
0%
#844
1%
#845
0%
#846
1%
#847
0%
#848
1%
#849
0%
#850
1%
#851
0%
#852
1%
#853
0%
#854
1%
#855
0%
#856
1%
#857
0%
#858
1%
#859
0%
#860
1%
#861
0%
#862
1%
#863
0%
#864
1%
#865
0%
#866
1%
#867
0%
#868
1%
#869
0%
#870
1%
#871
0%
#872
1%
#873
0%
#874
1%
#875
0%
#876
1%
#877
0%
#878
1%
#879
0%
#880
1%
#881
0%
#882
1%
#883
0%
#884
1%
#885
0%
#886
1%
#887
0%
#888
1%
#889
0%
#890
1%
#891
0%
#892
1%
#893
0%
#894
1%
#895
0%
#896
1%
#897
0%
#898
1%
#899
0%
#900
1%
#901
0%
#902
1%
#903
0%
#904
1%
#905
0%
#906
1%
#907
0%
#908
1%
#909
0%
#910
1%
#911
0%
#912
1%
#913
0%
#914
1%
#915
0%
#916
1%
#917
0%
#918
1%
#919
0%
#920
1%
#921
0%
#922
1%
#923
0%
#924
1%
#925
0%
#926
1%
#927
0%
#928
1%
#929
0%
#930
1%
#931
0%
#932
1%
#933
0%
#934
1%
#935
0%
#936
1%
#937
0%
#938
1%
#939
0%
#940
1%
#941
0%
#942
1%
#943
0%
#944
1%
#945
0%
#946
1%
#947
0%
#948
1%
#949
0%
#950
1%
#951
0%
#952
1%
#953
0%
#954
1%
#955
0%
#956
1%
#957
0%
#958
1%
#959
0%
#960
1%
#961
0%
#962
1%
#963
0%
#964
1%
#965
0%
#966
1%
#967
0%
#968
1%
#969
0%
#970
1%
#971
0%
#972
1%
#973
0%
#974
1%
#975
0%
#976
1%
#977
0%
#978
1%
#979
0%
#980
1%
#981
0%
#982
1%
#983
0%
#984
1%
#985
0%
#986
1%
#987
0%
#988
1%
#989
0%
#990
1%
#991
0%
#992
1%
#993
0%
#994
1%
#995
0%
#996
1%
#997
0%
#998
1%
#999
0%
#1000
1%
#1001
0%
#1002
1%
#1003
0%
#1004
1%
#1005
0%
#1006
1%
#1007
0%
#1008
1%
#1009
0%
#1010
1%
#1011
0%
#1012
1%
#1013
0%
#1014
1%
#1015
0%
#1016
1%
#1017
0%
#1018
1%
#1019
0%
#1020
1%
#1021
0%
#1022
1%
#1023
0%
#1024
1%
#1025
0%
#1026
1%
#1027
0%
#1028
1%
#1029
0%
#1030
1%
#1031
0%
#1032
1%
#1033
0%
#1034
1%
#1035
0%
#1036
1%
#1037
0%
#1038
1%
#1039
0%
#1040
1%
#1041
0%
#1042
1%
#1043
0%
#1044
1%
#1045
0%
#1046
1%
#1047
0%
#1048
1%
#1049
0%
#1050
1%
#1051
0%
#1052
1%
#1053
0%
#1054
1%
#1055
0%
#1056
1%
#1057
0%
#1058
1%
#1059
0%
#1060
1%
#1061
0%
#1062
1%
#1063
0%
#1064
1%
#1065
0%
#1066
1%
#1067
0%
#1068
1%
#1069
0%
#1070
1%
#1071
0%
#1072
1%
#1073
0%
#1074
1%
#1075
0%
#1076
1%
#1077
0%
#1078
1%
#1079
0%
#1080
1%
#1081
0%
#1082
1%
#1083
0%
#1084
1%
#1085
0%
#1086
1%
#1087
0%
#1088
1%
#1089
0%
#1090
1%
#1091
0%
#1092
1%
#1093
0%
#1094
1%
#1095
0%
#1096
1%
#1097
0%
#1098
1%
#1099
0%
#1100
1%
#1101
0%
#1102
1%
#1103
0%
#1104
1%
#1105
0%
#1106
1%
#1107
0%
#1108
1%
#1109
0%
#1110
1%
#1111
0%
#1112
1%
#1113
0%
#1114
1%
#1115
0%
#1116
1%
#1117
0%
#1118
1%
#1119
0%
#1120
1%
#1121
0%
#1122
1%
#1123
0%
#1124
1%
#1125
0%
#1126
1%
#1127
0%
#1128
1%
#1129
0%
#1130
1%
#1131
0%
#1132
1%
#1133
0%
#1134
1%
#1135
0%
#1136
1%
#1137
0%
#1138
1%
#1139
0%
#1140
1%
#1141
0%
#1142
1%
#1143
0%
#1144
1%
#1145
0%
#1146
1%
#1147
0%
#1148
1%
#1149
0%
#1150
1%
#1151
0%
#1152
1%
#1153
0%
#1154
1%
#1155
0%
#1156
1%
#1157
0%
#1158
1%
#1159
0%
#1160
1%
#1161
0%
#1162
1%
#1163
0%
#1164
1%
#1165
0%
#1166
1%
#1167
0%
#1168
1%
#1169
0%
#1170
1%
#1171
0%
#1172
1%
#1173
0%
#1174
1%
#1175
0%
#1176
1%
#1177
0%
#1178
1%
#1179
0%
#1180
1%
#1181
0%
#1182
1%
#1183
0%
#1184
1%
#1185
0%
#1186
1%
#1187
0%
#1188
1%
#1189
0%
#1190
1%
#1191
0%
#1192
1%
#1193
0%
#1194
1%
#1195
0%
#1196
1%
#1197
0%
#1198
1%
#1199
0%
#1200
1%
#1201
0%
#1202
1%
#1203
0%
#1204
1%
#1205
0%
#1206
1%
#1207
0%
#1208
1%
#1209
0%
#1210
1%
#1211
0%
#1212
1%
#1213
0%
#1214
1%
#1215
0%
#1216
1%
#1217
0%
#1218
1%
#1219
0%
#1220
1%
#1221
0%
#1222
1%
#1223
0%
#1224
1%
#1225
0%
#1226
1%
#1227
0%
#1228
1%
#1229
0%
#1230
1%
#1231
0%
#1232
1%
#1233
0%
#1234
1%
#1235
0%
#1236
1%
#1237
0%
#1238
1%
#1239
0%
#1240
1%
#1241
0%
#1242
1%
#1243
0%
#1244
1%
#1245
0%
#1246
1%
#1247
0%
#1248
1%
#1249
0%
#1250
1%
#1251
0%
#1252
1%
#1253
0%
#1254
1%
#1255
0%
#1256
1%
#1257
0%
#1258
1%
#1259
0%
#1260
1%
#1261
0%
#1262
1%
#1263
0%
#1264
1%
#1265
0%
#1266
1%
#1267
0%
#1268
1%
#1269
0%
#1270
1%
#1271
0%
#1272
1%
#1273
0%
#1274
1%
#1275
0%
#1276
1%
#1277
0%
#1278
1%
#1279
0%
#1280
1%
#1281
0%
#1282
1%
#1283
0%
#1284
1%
#1285
0%
#1286
1%
#1287
0%
#1288
1%
#1289
0%
#1290
1%
#1291
0%
#1292
1%
#1293
0%
#1294
1%
#1295
0%
#1296
1%
#1297
0%
#1298
1%
#1299
0%
#1300
1%
#1301
0%
#1302
1%
#1303
0%
#1304
1%
#1305
0%
#1306
1%
#1307
0%
#1308
1%
#1309
0%
#1310
1%
#1311
0%
#1312
1%
#1313
0%
#1314
1%
#1315
0%
#1316
1%
#1317
0%
#1318
1%
#1319
0%
#1320
1%
#1321
0%
#1322
1%
#1323
0%
#1324
1%
#1325
0%
#1326
1%
#1327
0%
#1328
1%
#1329
0%
#1330
1%
#1331
0%
#1332
1%
#1333
0%
#1334
1%
#1335
0%
#1336
1%
#1337
0%
#1338
1%
#1339
0%
#1340
1%
#1341
0%
#1342
1%
#1343
0%
#1344
1%
#1345
0%
#1346
1%
#1347
0%
#1348
1%
#1349
0%
#1350
1%
#1351
0%
#1352
1%
#1353
0%
#1354
1%
#1355
0%
#1356
1%
#1357
0%
#1358
1%
#1359
0%
#1360
1%
#1361
0%
#1362
1%
#1363
0%
#1364
1%
#1365
0%
#1366
1%
#1367
0%
#1368
1%
#1369
0%
#1370
1%
#1371
0%
#1372
1%
#1373
0%
#1374
1%
#1375
0%
#1376
1%
#1377
0%
#1378
1%
#1379
0%
#1380
1%
#1381
0%
#1382
1%
#1383
0%
#1384
1%
#1385
0%
#1386
1%
#1387
0%
#1388
1%
#1389
0%
#1390
1%
#1391
0%
#1392
1%
#1393
0%
#1394
1%
#1395
0%
#1396
1%
#1397
0%
#1398
1%
#1399
0%
#1400
1%
#1401
0%
#1402
1%
#1403
0%
#1404
1%
#1405
0%
#1406
1%
#1407
0%
#1408
1%
#1409
0%
#1410
1%
#1411
0%
#1412
1%
#1413
0%
#1414
1%
#1415
0%
#1416
1%
#1417
0%
#1418
1%
#1419
0%
#1420
1%
#1421
0%
#1422
1%
#1423
0%
#1424
1%
#1425
0%
#1426
1%
#1427
0%
#1428
1%
#1429
0%
#1430
1%
#1431
0%
#1432
1%
#1433
0%
#1434
1%
#1435
0%
#1436
1%
#1437
0%
#1438
1%
#1439
0%
#1440
1%
#1441
0%
#1442
1%
#1443
0%
#1444
1%
#1445
0%
#1446
1%
#1447
0%
#1448
1%
#1449
0%
#1450
1%
#1451
0%
#1452
1%
#1453
0%
#1454
1%
#1455
0%
#1456
1%
#1457
0%
#1458
1%
#1459
0%
#1460
1%
#1461
0%
#1462
1%
#1463
0%
#1464
1%
#1465
0%
#1466
1%
#1467
0%
#1468
1%
#1469
0%
#1470
1%
#1471
0%
#1472
1%
#1473
0%
#1474
1%
#1475
0%
#1476
1%
#1477
0%
#1478
1%
#1479
0%
#1480
1%
#1481
0%
#1482
1%
#1483
0%
#1484
1%
#1485
0%
#1486
1%
#1487
0%
#1488
1%
#1489
0%
#1490
1%
#1491
0%
#1492
1%
#1493
0%
#1494
1%
#1495
0%
#1496
1%
#1497
0%
#1498
1%
#1499
0%
#1500
1%
#1501
0%
#1502
1%
#1503
0%
#1504
1%
#1505
0%
#1506
1%
#1507
0%
#1508
1%
#1509
0%
#1510
1%
#1511
0%
#1512
1%
#1513
0%
#1514
1%
#1515
0%
#1516
1%
#1517
0%
#1518
1%
#1519
0%
#1520
1%
#1521
0%
#1522
1%
#1523
0%
#1524
1%
#1525
0%
#1526
1%
#1527
0%
#1528
1%
#1529
0%
#1530
1%
#1531
0%
#1532
1%
#1533
0%
#1534
1%
#1535
0%
#1536
1%
#1537
0%
#1538
1%
#1539
0%
#1540
1%
#1541
0%
#1542
1%
#1543
0%
#1544
1%
#1545
0%
#1546
1%
#1547
0%
#1548
1%
#1549
0%
#1550
1%
#1551
0%
#1552
1%
#1553
0%
#1554
1%
#1555
0%
#1556
1%
#1557
0%
#1558
1%
#1559
0%
#1560
1%
#1561
0%
#1562
1%
#1563
0%
#1564
1%
#1565
0%
#1566
1%
#1567
0%
#1568
1%
#1569
0%
#1570
1%
#1571
0%
#1572
1%
#1573
0%
#1574
1%
#1575
0%
#1576
1%
#1577
0%
#1578
1%
#1579
0%
#1580
1%
#1581
0%
#1582
1%
#1583
0%
#1584
1%
#1585
0%
#1586
1%
#1587
0%
#1588
1%
#1589
0%
#1590
1%
#1591
0%
#1592
1%
#1593
0%
#1594
1%
#1595
0%
#1596
1%
#1597
0%
#1598
1%
#1599
0%
#1600
1%
#1601
0%
#1602
1%
#1603
0%
#1604
1%
#1605
0%
#1606
1%
#1607
0%
#1608
1%
#1609
0%
#1610
1%
#1611
0%
#1612
1%
#1613
0%
#1614
1%
#1615
0%
#1616
1%
#1617
0%
#1618
1%
#1619
0%
#1620
1%
#1621
0%
#1622
1%
#1623
0%
#1624
1%
#1625
0%
#1626
1%
#1627
0%
#1628
1%
#1629
0%
#1630
1%
#1631
0%
#1632
1%
#1633
0%
#1634
1%
#1635
0%
#1636
1%
#1637
0%
#1638
1%
#1639
0%
#1640
1%
#1641
0%
#1642
1%
#1643
0%
#1644
1%
#1645
0%
#1646
1%
#1647
0%
#1648
1%
#1649
0%
#1650
1%
#1651
0%
#1652
1%
#1653
0%
#1654
1%
#1655
0%
#1656
1%
#1657
0%
#1658
1%
#1659
0%
#1660
1%
#1661
0%
#1662
1%
#1663
0%
#1664
1%
#1665
0%
#1666
1%
#1667
0%
#1668
1%
#1669
0%
#1670
1%
#1671
0%
#1672
1%
#1673
0%
#1674
1%
#1675
0%
#1676
1%
#1677
0%
#1678
1%
#1679
0%
#1680
1%
#1681
0%
#1682
1%
#1683
0%
#1684
1%
#1685
0%
#1686
1%
#1687
0%
#1688
1%
#1689
0%
#1690
1%
#1691
0%
#1692
1%
#1693
0%
#1694
1%
#1695
0%
#1696
1%
#1697
0%
#1698
1%
#1699
0%
#1700
1%
#1701
0%
#1702
1%
#1703
0%
#1704
1%
#1705
0%
#1706
1%
#1707
0%
#1708
1%
#1709
0%
#1710
1%
#1711
0%
#1712
1%
#1713
0%
#1714
1%
#1715
0%
#1716
1%
#1717
0%
#1718
1%
#1719
0%
#1720
1%
#1721
0%
#1722
1%
#1723
0%
#1724
1%
#1725
0%
#1726
1%
#1727
0%
#1728
1%
#1729
0%
#1730
1%
#1731
0%
#1732
1%
#1733
0%
#1734
1%
#1735
0%
#1736
1%
#1737
0%
#1738
1%
#1739
0%
#1740
1%
#1741
0%
#1742
1%
#1743
0%
#1744
1%
#1745
0%
#1746
1%
#1747
0%
#1748
1%
#1749
0%
#1750
1%
#1751
0%
#1752
1%
#1753
0%
#1754
1%
#1755
0%
#1756
1%
#1757
0%
#1758
1%
#1759
0%
#1760
1%
#1761
0%
#1762
1%
#1763
0%
#1764
1%
#1765
0%
#1766
1%
#1767
0%
#1768
1%
#1769
0%
#1770
1%
#1771
0%
#1772
1%
#1773
0%
#1774
1%
#1775
0%
#1776
1%
#1777
0%
#1778
1%
#1779
0%
#1780
1%
#1781
0%
#1782
1%
#1783
0%
#1784
1%
#1785
0%
#1786
1%
#1787
0%
#1788
1%
#1789
0%
#1790
1$
1%
#1791
0%
#1792
0$
1%
b00000010 &
b00000010 '
#1793
0%
#1794
1%
#1795
0%
#1796
1%
#1797
0%
#1798
1%
#1799
0%
#1800
1%
#1801
0%
#1802
1%
#1803
0%
#1804
1%
#1805
0%
#1806
1%
#1807
0%
#1808
1%
#1809
0%
#1810
1%
#1811
0%
#1812
1%
#1813
0%
#1814
1%
#1815
0%
#1816
1%
#1817
0%
#1818
1%
#1819
0%
#1820
1%
#1821
0%
#1822
1%
#1823
0%
#1824
1%
#1825
0%
#1826
1%
#1827
0%
#1828
1%
#1829
0%
#1830
1%
#1831
0%
#1832
1%
#1833
0%
#1834
1%
#1835
0%
#1836
1%
#1837
0%
#1838
1%
#1839
0%
#1840
1%
#1841
0%
#1842
1%
#1843
0%
#1844
1%
#1845
0%
#1846
1%
#1847
0%
#1848
1%
#1849
0%
#1850
1%
#1851
0%
#1852
1%
#1853
0%
#1854
1%
#1855
0%
#1856
1%
#1857
0%
#1858
1%
#1859
0%
#1860
1%
#1861
0%
#1862
1%
#1863
0%
#1864
1%
#1865
0%
#1866
1%
#1867
0%
#1868
1%
#1869
0%
#1870
1%
#1871
0%
#1872
1%
#1873
0%
#1874
1%
#1875
0%
#1876
1%
#1877
0%
#1878
1%
#1879
0%
#1880
1%
#1881
0%
#1882
1%
#1883
0%
#1884
1%
#1885
0%
#1886
1%
#1887
0%
#1888
1%
#1889
0%
#1890
1%
#1891
0%
#1892
1%
#1893
0%
#1894
1%
#1895
0%
#1896
1%
#1897
0%
#1898
1%
#1899
0%
#1900
1%
#1901
0%
#1902
1%
#1903
0%
#1904
1%
#1905
0%
#1906
1%
#1907
0%
#1908
1%
#1909
0%
#1910
1%
#1911
0%
#1912
1%
#1913
0%
#1914
1%
#1915
0%
#1916
1%
#1917
0%
#1918
1%
#1919
0%
#1920
1$
1%
#1921
0%
#1922
0$
1%
b00000100 &
b00000100 '
#1923
0%
#1924
1%
#1925
0%
#1926
1%
#1927
0%
#1928
1%
#1929
0%
#1930
1%
#1931
0%
#1932
1%
#1933
0%
#1934
1%
#1935
0%
#1936
1%
#1937
0%
#1938
1%
#1939
0%
#1940
1%
#1941
0%
#1942
1%
#1943
0%
#1944
1%
#1945
0%
#1946
1%
#1947
0%
#1948
1%
#1949
0%
#1950
1%
#1951
0%
#1952
1%
#1953
0%
#1954
1%
#1955
0%
#1956
1%
#1957
0%
#1958
1%
#1959
0%
#1960
1%
#1961
0%
#1962
1%
#1963
0%
#1964
1%
#1965
0%
#1966
1%
#1967
0%
#1968
1%
#1969
0%
#1970
1%
#1971
0%
#1972
1%
#1973
0%
#1974
1%
#1975
0%
#1976
1%
#1977
0%
#1978
1%
#1979
0%
#1980
1%
#1981
0%
#1982
1%
#1983
0%
#1984
1%
#1985
0%
#1986
1%
#1987
0%
#1988
1%
#1989
0%
#1990
1%
#1991
0%
#1992
1%
#1993
0%
#1994
1%
#1995
0%
#1996
1%
#1997
0%
#1998
1%
#1999
0%
#2000
1%
#2001
0%
#2002
1%
#2003
0%
#2004
1%
#2005
0%
#2006
1%
#2007
0%
#2008
1%
#2009
0%
#2010
1%
#2011
0%
#2012
1%
#2013
0%
#2014
1%
#2015
0%
#2016
1%
#2017
0%
#2018
1%
#2019
0%
#2020
1%
#2021
0%
#2022
1%
#2023
0%
#2024
1%
#2025
0%
#2026
1%
#2027
0%
#2028
1%
#2029
0%
#2030
1%
#2031
0%
#2032
1%
#2033
0%
#2034
1%
#2035
0%
#2036
1%
#2037
0%
#2038
1%
#2039
0%
#2040
1%
#2041
0%
#2042
1%
#2043
0%
#2044
1%
#2045
0%
#2046
1%
#2047
0%
#2048
1%
#2049
0%
#2050
1%
#2051
0%
#2052
1%
#2053
0%
#2054
1%
#2055
0%
#2056
1%
#2057
0%
#2058
1%
#2059
0%
#2060
1%
#2061
0%
#2062
1%
#2063
0%
#2064
1%
#2065
0%
#2066
1%
#2067
0%
#2068
1%
#2069
0%
#2070
1$
1%
#2071
0%
#2072
0$
1%
b00001001 &
b00001001 '
